Workbook

Sheet IS
A2: HCL Technologies Ltd (HCLTECH)
A5: Income Statement (All numbers in INR crores except EPS and DPS) | B5: FY 2014 | C5: FY 2015 | D5: FY 2016 | E5: FY 2017 | F5: FY 2018 | G5: FY 2019 | H5: FY 2020 | I5: FY 2021 | J5: FY 2022 | K5: FY 2023
A6: 'Total Revenue' | B6: 32821.06 | C6: 37840.68 | D6: 32006.83 | E6: 48643 | F6: 51799 | G6: 61370 | H6: 71265 | I6: 76306 | J6: 86718 | K6: 102814
A7: y-o-y grwoth in revenue | C7: =C6/B6-1 -> 0.152939 | D7: =D6/C6-1 -> -0.15416874 | E7: =E6/D6-1 -> 0.51976937 | F7: =F6/E6-1 -> 0.064880867 | G7: =G6/F6-1 -> 0.18477191 | H7: =H6/G6-1 -> 0.16123513 | I7: =I6/H6-1 -> 0.070735985 | J7: =J6/I6-1 -> 0.13645061 | K7: =K6/J6-1 -> 0.18561314
A8: '- Raw Materials' | B8: 920.92 | C8: 1306.38 | D8: 812.73 | E8: 826 | F8: 1251 | G8: 1615 | H8: 1536 | I8: 1698 | J8: 1473 | K8: 2072
A9: '- Power & Fuel Cost' | B9: 241.99 | C9: 264.88 | D9: 210.53 | E9: 307 | F9: 313 | G9: 336 | H9: 307 | I9: 275 | J9: 291 | K9: 328
A10: '- Employee Cost' | B10: 14906.36 | C10: 17726.43 | D10: 15203.25 | E10: 22866 | F10: 24729 | G10: 29283 | H10: 34928 | I10: 38853 | J10: 46130 | K10: 55280
A11: '- Selling & Administrative Expenses' | B11: 2602.09 | C11: 2853.17 | D11: 2205.52 | E11: 2988 | F11: 2810 | G11: 3519 | H11: 3050 | I11: 1681 | J11: 1866 | K11: 2687
A12: '- Operating & Other expenses' | B12: 5437.01 | C12: 6077.78 | D12: 6050.36 | E12: 10197 | F12: 10220 | G12: 11748 | H12: 13539 | I12: 12824 | J12: 15362 | K12: 18461
A13: '= EBITDA' | B13: 8712.69 | C13: 9612.04 | D13: 7524.44 | E13: 11459 | F13: 12476 | G13: 14869 | H13: 17905 | I13: 20975 | J13: 21596 | K13: 23986
A14: '- Depreciation/Amortization' | B14: 680.86 | C14: 403.75 | D14: 409.86 | E14: 828 | F14: 1383 | G14: 2073 | H14: 3420 | I14: 4611 | J14: 4326 | K14: 4145
A15: '= PBIT' | B15: 8031.83 | C15: 9208.29 | D15: 7114.58 | E15: 10631 | F15: 11093 | G15: 12796 | H15: 14485 | I15: 16364 | J15: 17270 | K15: 19841
A16: '- Interest & Other Items' | B16: 114.5 | C16: 91.23 | D16: 73.9 | E16: 89 | F16: 69 | G16: 174 | H16: 505 | I16: 511 | J16: 319 | K16: 353
A17: '= PBT' | B17: 7917.33 | C17: 9117.06 | D17: 7040.68 | E17: 10542 | F17: 11024 | G17: 12622 | H17: 13980 | I17: 15853 | J17: 16951 | K17: 19488
A18: '- Taxes & Other Items' | B18: 1407.82 | C18: 1799.99 | D18: 1438.25 | E18: 1936 | F18: 2303 | G18: 2502 | H18: 2923 | I18: 4708 | J18: 3452 | K18: 4637
A19: '= Net Income' | B19: 6509.51 | C19: 7317.07 | D19: 5602.43 | E19: 8606 | F19: 8721 | G19: 10120 | H19: 11057 | I19: 11145 | J19: 13499 | K19: 14851
... A23: 'Payout ratio' | B23: 0.11 | C23: 0.58 | D23: 0.4 | E23: 0.4 | F23: 0.19 | G23: 0.11 | H23: 0.25 | I23: 0.24 | J23: 0.84 | K23: 0.88

Sheet BS
A2: HCL Technologies Ltd (HCLTECH)
A5: Balance Sheet (All numbers in INR crores) | B5: FY 2014 | C5: FY 2015 | D5: FY 2016 | E5: FY 2017 | F5: FY 2018 | G5: FY 2019 | H5: FY 2020 | I5: FY 2021 | J5: FY 2022 | K5: FY 2023
A6: 'Cash and Short Term Investments' | B6: 9413.59 | C6: 10548.81 | D6: 9871.07 | E6: 10190 | F6: 6375 | G6: 10092 | H6: 11965 | I6: 15661 | J6: 18875 | K6: 20109
A7: '+ Total Receivables' | B7: 5682.84 | C7: 6538.69 | D7: 7721.14 | E7: 8301 | F7: 9639 | G7: 11706 | H7: 14131 | I7: 17525 | J7: 20671 | K7: 25506
A8: '+ Total Inventory' | B8: 122.3 | C8: 157.61 | D8: 264.48 | E8: 276 | F8: 172 | G8: 91 | H8: 91 | I8: 94 | J8: 161 | K8: 228
A9: '+ Other Current Assets' | B9: 4110.9 | C9: 5801.69 | D9: 7125.01 | E9: 7696 | F9: 8372 | G9: 7833 | H9: 12233 | I9: 9771 | J9: 8334 | K9: 7734
A10: '= Total Current Assets (A1)' | B10: 19329.63 | C10: 23046.8 | D10: 24981.7 | E10: 26463 | F10: 24558 | G10: 29722 | H10: 38420 | I10: 43051 | J10: 48041 | K10: 53577
A11: 'Loans & Advances' | B11: - | C11: - | D11: - | E11: - | F11: - | G11: - | H11: - | I11: - | J11: - | K11: -
A12: '+ Net Property/Plant/Equipment' | B12: 3272.25 | C12: 4026.16 | D12: 4446.15 | E12: 4979 | F12: 5472 | G12: 6328 | H12: 15210 | I12: 14129 | J12: 12735 | K12: 11840
A13: '+ Goodwill & Intangibles' | B13: 4702.64 | C13: 4800.63 | D13: 5880.84 | E13: 10704 | F13: 13601 | G13: 16795 | H13: 22680 | I13: 23328 | J13: 22471 | K13: 22819
A14: '+ Long Term Investments' | B14: 55.4 | C14: 106.81 | D14: 161.91 | E14: 160 | F14: 303 | G14: 85 | H14: 77 | I14: 89 | J14: 112 | K14: 110
A15: '+ Deferred Tax Assets (Net)' | B15: 814.96 | C15: 789.71 | D15: 1811.09 | E15: 1652 | F15: 1803 | G15: 2229 | H15: 2230 | I15: 1034 | J15: 1064 | K15: 1091
A16: '+ Other Assets' | B16: 1804.81 | C16: 2474.56 | D16: 2058.91 | E16: 1804 | F16: 2252 | G16: 3190 | H16: 4202 | I16: 4416 | J16: 4498 | K16: 3813
A17: '= Non Current Assets (A2)' | B17: 10650.06 | C17: 12197.87 | D17: 14358.9 | E17: 19299 | F17: 23431 | G17: 28627 | H17: 44399 | I17: 42996 | J17: 40880 | K17: 39673
A18: 'Total Assets (A1 + A2)' | B18: 29979.69 | C18: 35244.67 | D18: 39340.6 | E18: 45762 | F18: 47989 | G18: 58349 | H18: 82819 | I18: 86047 | J18: 88921 | K18: 93250
A19: 'Accounts Payable' | B19: 1264.43 | C19: 1409.45 | D19: 1277.86 | E19: 2853 | F19: 2001 | G19: 1954 | H19: 1807 | I19: 6091 | J19: 6901 | K19: 6875
A20: '+ Total Deposits' | B20: - | C20: - | D20: - | E20: - | F20: - | G20: - | H20: - | I20: - | J20: - | K20: -
A21: '+ Other Current Liabilities' | B21: 7977.35 | C21: 8535.6 | D21: 8550.59 | E21: 8482 | F21: 8106 | G21: 10345 | H21: 21923 | I21: 11292 | J21: 11874 | K21: 14556
A22: '= Current Liabilities' | B22: 9241.78 | C22: 9945.05 | D22: 9828.45 | E22: 11335 | F22: 10107 | G22: 12299 | H22: 23730 | I22: 17383 | J22: 18775 | K22: 21431
A23: 'Total Long Term Debt' | B23: 200.64 | C23: 167.89 | D23: 737.4 | E23: 383 | F23: 338 | G23: 2977 | H23: 5027 | I23: 5731 | J23: 5582 | K23: 3775
A24: '+ Deferred Tax Liabilities (Net)' | B24: - | C24: - | D24: - | E24: - | F24: - | G24: - | H24: - | I24: - | J24: - | K24: -
A25: '+ Other Liabilities' | B25: 930.11 | C25: 825.21 | D25: 1173.32 | E25: 922 | F25: 1158 | G25: 1604 | H25: 2641 | I25: 2851 | J25: 2558 | K25: 2646
A26: '= Non Current Liabilities' | B26: 1130.75 | C26: 993.1 | D26: 1910.72 | E26: 1305 | F26: 1496 | G26: 4581 | H26: 7668 | I26: 8582 | J26: 8140 | K26: 6421
A27: 'Total Liabilities' | B27: 10372.53 | C27: 10938.15 | D27: 11739.17 | E27: 12640 | F27: 11603 | G27: 16880 | H27: 31398 | I27: 25965 | J27: 26915 | K27: 27852
A28: 'Common Stock' | B28: 140 | C28: 281.2 | D28: 282.08 | E28: 285 | F28: 278 | G28: 271 | H28: 543 | I28: 543 | J28: 543 | K28: 543
A29: '+ Additional Paid-in Capital' | B29: 1933.97 | C29: 1881.21 | D29: 1963.01 | E29: 3244 | F29: 5 | G29: 2 | H29: 7 | I29: 7 | J29: 7 | K29: 7
A30: '+ Reserves & Surplus' | B30: 17468.21 | C30: 22061.98 | D30: 25145.63 | E30: 29420 | F30: 36103 | G30: 41093 | H30: 50717 | I30: 59363 | J30: 61364 | K30: 64855
A31: '+ Minority Interest' | B31: 57.33 | C31: 82.11 | D31: 210.66 | E31: 173 | F31: 0 | G31: 103 | H31: 154 | I31: 169 | J31: 92 | K31: -7
A32: '+ Other Equity' | B32: 7.65 | C32: 0.02 | D32: 0.05 | E32: 0 | F32: 0 | G32: 0 | H32: 0 | I32: 0 | J32: 0 | K32: 0
A33: 'Total Equity' | B33: 19607.16 | C33: 24306.52 | D33: 27601.43 | E33: 33122 | F33: 36386 | G33: 41469 | H33: 51421 | I33: 60082 | J33: 62006 | K33: 65398
A34: 'Total Liabilities & Shareholder's Equity' | B34: 29979.69 | C34: 35244.67 | D34: 39340.6 | E34: 45762 | F34: 47989 | G34: 58349 | H34: 82819 | I34: 86047 | J34: 88921 | K34: 93250

Sheet CFS
A2: HCL Technologies Ltd (HCLTECH)
A5: Cash Flow Statement (All numbers in INR crores) | B5: FY 2014 | C5: FY 2015 | D5: FY 2016 | E5: FY 2017 | F5: FY 2018 | G5: FY 2019 | H5: FY 2020 | I5: FY 2021 | J5: FY 2022 | K5: FY 2023
A6: 'Cash from Operating Activities' | B6: 6456.78 | C6: 5539.2 | D6: 3822.62 | E6: 8995 | F6: 8328 | G6: 8971 | H6: 13359 | I6: 19618 | J6: 16900 | K6: 18009
A7: '+ Cash from Investing Activities' | B7: -4842.28 | C7: -2087.57 | D7: -2208.43 | E7: -3890 | F7: -2236 | G7: -3256 | H7: -12332 | I7: -5665 | J7: 1597 | K7: -3573
A8: '+ Cash from Financing Activities' | B8: -1307.97 | C8: -3140.34 | D8: -2237.09 | E8: -4517 | F8: -5714 | G8: -1471 | H8: -3168 | I8: -11192 | J8: -14508 | K8: -15881
A9: '= Net Change in Cash' | B9: 306.53 | C9: 311.29 | D9: -622.9 | E9: 588 | F9: 378 | G9: 4244 | H9: -2141 | I9: 2761 | J9: 3989 | K9: -1445
A10: 'Changes in Working Capital' | B10: -1689.02 | C10: -2962.5 | D10: -2911.97 | E10: -1686 | F10: -3590 | G10: -5087 | H10: -4118 | I10: -404 | J10: -3992 | K10: -5003
A11: 'Capital Expenditures' | B11: 719.56 | C11: 1208.16 | D11: 941.84 | E11: 3921 | F11: 5344 | G11: 3465 | H11: 1866 | I11: 1904 | J11: 1645 | K11: 1661
A12: 'Free Cash Flow' | B12: 5737.22 | C12: 4331.04 | D12: 2880.78 | E12: 5074 | F12: 2984 | G12: 5506 | H12: 11493 | I12: 17714 | J12: 15255 | K12: 16348

Sheet Ratio Analysis-hcl
A2: Profitability Ratios | B2: FY 2014 | C2: FY 2015 | D2: FY 2016 | E2: FY 2017 | F2: FY 2018 | G2: FY 2019 | H2: FY 2020 | I2: FY 2021 | J2: FY 2022 | K2: FY 2023
A3: EBITDA Margin | B3: =IS!B13/IS!B6 -> 0.26546035 | C3: =IS!C13/IS!C6 -> 0.25401341 | D3: =IS!D13/IS!D6 -> 0.23508857 | E3: =IS!E13/IS!E6 -> 0.23557346 | F3: =IS!F13/IS!F6 -> 0.24085407 | G3: =IS!G13/IS!G6 -> 0.2422845 | H3: =IS!H13/IS!H6 -> 0.25124535 | I3: =IS!I13/IS!I6 -> 0.27488009 | ... K3: =IS!K13/IS!K6 -> 0.23329508
A4: EBIT Margin | B4: =IS!B15/IS!B6 -> 0.24471574 | C4: =IS!C15/IS!C6 -> 0.24334367 | D4: =IS!D15/IS!D6 -> 0.22228318 | E4: =IS!E15/IS!E6 -> 0.21855149 | F4: =IS!F15/IS!F6 -> 0.21415471 | G4: =IS!G15/IS!G6 -> 0.20850578 | H4: =IS!H15/IS!H6 -> 0.20325545 | I4: =IS!I15/IS!I6 -> 0.21445234 | ... K4: =IS!K15/IS!K6 -> 0.19297956
A5: EBT Margin | B5: =IS!B17/IS!B6 -> 0.24122713 | C5: =IS!C17/IS!C6 -> 0.24093277 | D5: =IS!D17/IS!D6 -> 0.2199743 | E5: =IS!E17/IS!E6 -> 0.21672183 | F5: =IS!F17/IS!F6 -> 0.21282264 | G5: =IS!G17/IS!G6 -> 0.20567052 | H5: =IS!H17/IS!H6 -> 0.19616923 | I5: =IS!I17/IS!I6 -> 0.20775562 | ... K5: =IS!K17/IS!K6 -> 0.18954617
A6: PAT Margin | B6: =IS!B19/IS!B6 -> 0.19833333 | C6: =IS!C19/IS!C6 -> 0.19336518 | D6: =IS!D19/IS!D6 -> 0.17503858 | E6: =IS!E19/IS!E6 -> 0.17692165 | F6: =IS!F19/IS!F6 -> 0.16836232 | G6: =IS!G19/IS!G6 -> 0.16490142 | H6: =IS!H19/IS!H6 -> 0.1551533 | I6: =IS!I19/IS!I6 -> 0.14605667 | ... K6: =IS!K19/IS!K6 -> 0.14444531
A7: ROA | C7: =IS!C19/AVERAGE(BS!B18:C18) -> 0.22436617 | D7: =IS!D19/AVERAGE(BS!C18:D18) -> 0.15022886 | E7: =IS!E19/AVERAGE(BS!D18:E18) -> 0.20224999 | F7: =IS!F19/AVERAGE(BS!E18:F18) -> 0.18604602 | G7: =IS!G19/AVERAGE(BS!F18:G18) -> 0.19033647 | H7: =IS!H19/AVERAGE(BS!G18:H18) -> 0.15665023 | I7: =IS!I19/AVERAGE(BS!H18:I18) -> 0.13199815 | J7: =IS!J19/AVERAGE(BS!I18:J18) -> 0.1543025 | K7: =IS!K19/AVERAGE(BS!J18:K18) -> 0.16304461
A8: ROE | C8: =IS!C19/AVERAGE(BS!B33:C33) -> 0.33324786 | D8: =IS!D19/AVERAGE(BS!C33:D33) -> 0.21586019 | E8: =IS!E19/AVERAGE(BS!D33:E33) -> 0.28344907 | F8: =IS!F19/AVERAGE(BS!E33:F33) -> 0.25093514 | G8: =IS!G19/AVERAGE(BS!F33:G33) -> 0.25997046 | H8: =IS!H19/AVERAGE(BS!G33:H33) -> 0.23806653 | I8: =IS!I19/AVERAGE(BS!H33:I33) -> 0.19990494 | J8: =IS!J19/AVERAGE(BS!I33:J33) -> 0.22113557 | K8: =IS!K19/AVERAGE(BS!J33:K33) -> 0.2331324
A9: ROCE | C9: =IS!C15/(AVERAGE(BS!B33:C33)+AVERAGE(BS!B23:C23)) -> 0.41589117 | D9: =IS!D15/(AVERAGE(BS!C33:D33)+AVERAGE(BS!C23:D23)) -> 0.26942411 | E9: =IS!E15/(AVERAGE(BS!D33:E33)+AVERAGE(BS!D23:E23)) -> 0.34380148 | F9: =IS!F15/(AVERAGE(BS!E33:F33)+AVERAGE(BS!E23:F23)) -> 0.31590938 | G9: =IS!G15/(AVERAGE(BS!F33:G33)+AVERAGE(BS!F23:G23)) -> 0.3152889 | H9: =IS!H15/(AVERAGE(BS!G33:H33)+AVERAGE(BS!G23:H23)) -> 0.28713303 | I9: =IS!I15/(AVERAGE(BS!H33:I33)+AVERAGE(BS!H23:I23)) -> 0.26768961 | J9: =IS!J15/(AVERAGE(BS!I33:J33)+AVERAGE(BS!I23:J23)) -> 0.2589186 | K9: =IS!K15/(AVERAGE(BS!J33:K33)+AVERAGE(BS!J23:K23)) -> 0.29015582
A11: Liquidity Ratios | B11: FY 2014 | C11: FY 2015 | D11: FY 2016 | E11: FY 2017 | F11: FY 2018 | G11: FY 2019 | H11: FY 2020 | I11: FY 2021 | J11: FY 2022 | K11: FY 2023
A12: Current Ratio | B12: =BS!B10/BS!B22 -> 2.0915484 | C12: =BS!C10/BS!C22 -> 2.3174142 | D12: =BS!D10/BS!D22 -> 2.5417741 | E12: =BS!E10/BS!E22 -> 2.3346273 | F12: =BS!F10/BS!F22 -> 2.4298011 | G12: =BS!G10/BS!G22 -> 2.4166192 | H12: =BS!H10/BS!H22 -> 1.6190476 | I12: =BS!I10/BS!I22 -> 2.4766151 | ... K12: =BS!K10/BS!K22 -> 2.4999767
A13: Quick Ratio | B13: =(BS!B6+BS!B7)/BS!B22 -> 1.6334981 | C13: =(BS!C6+BS!C7)/BS!C22 -> 1.7181915 | D13: =(BS!D6+BS!D7)/BS!D22 -> 1.7899272 | E13: =(BS!E6+BS!E7)/BS!E22 -> 1.6313189 | F13: =(BS!F6+BS!F7)/BS!F22 -> 1.5844464 | G13: =(BS!G6+BS!G7)/BS!G22 -> 1.7723392 | H13: =(BS!H6+BS!H7)/BS!H22 -> 1.099705 | I13: =(BS!I6+BS!I7)/BS!I22 -> 1.9091066 | ... K13: =(BS!K6+BS!K7)/BS!K22 -> 2.1284588
A14: Cash Ratio | B14: =BS!B6/BS!B22 -> 1.0185906 | C14: =BS!C6/BS!C22 -> 1.0607096 | D14: =BS!D6/BS!D22 -> 1.0043364 | E14: =BS!E6/BS!E22 -> 0.89898544 | F14: =BS!F6/BS!F22 -> 0.63075096 | G14: =BS!G6/BS!G22 -> 0.82055452 | H14: =BS!H6/BS!H22 -> 0.50421408 | I14: =BS!I6/BS!I22 -> 0.9009377 | ... K14: =BS!K6/BS!K22 -> 0.93831366
A15: Defensive Interval | B15: =BS!B10/(SUM(IS!B8:B12)/365) -> 292.65002 | C15: =BS!C10/(SUM(IS!C8:C12)/365) -> 297.99813 | D15: =BS!D10/(SUM(IS!D8:D12)/365) -> 372.44405 | E15: =BS!E10/(SUM(IS!E8:E12)/365) -> 259.76213 | F15: =BS!F10/(SUM(IS!F8:F12)/365) -> 227.9498 | G15: =BS!G10/(SUM(IS!G8:G12)/365) -> 233.2967 | H15: =BS!H10/(SUM(IS!H8:H12)/365) -> 262.80547 | I15: =BS!I10/(SUM(IS!I8:I12)/365) -> 283.99297 | ... K15: =BS!K10/(SUM(IS!K8:K12)/365) -> 248.07943
A17: Solvency Ratios | B17: FY 2014 | C17: FY 2015 | D17: FY 2016 | E17: FY 2017 | F17: FY 2018 | G17: FY 2019 | H17: FY 2020 | I17: FY 2021 | J17: FY 2022 | K17: FY 2023
A18: A/E | B18: =BS!B18/BS!B33 -> 1.5290175 | C18: =BS!C18/BS!C33 -> 1.4500089 | D18: =BS!D18/BS!D33 -> 1.4253102 | E18: =BS!E18/BS!E33 -> 1.3816195 | F18: =BS!F18/BS!F33 -> 1.3188864 | G18: =BS!G18/BS!G33 -> 1.4070511 | H18: =BS!H18/BS!H33 -> 1.6106066 | I18: =BS!I18/BS!I33 -> 1.4321594 | ... K18: =BS!K18/BS!K33 -> 1.4258846
A19: D/E | B19: =BS!B23/BS!B33 -> 0.010232997 | C19: =BS!C23/BS!C33 -> 0.0069072002 | D19: =BS!D23/BS!D33 -> 0.026716007 | E19: =BS!E23/BS!E33 -> 0.011563311 | F19: =BS!F23/BS!F33 -> 0.0092892871 | G19: =BS!G23/BS!G33 -> 0.071788565 | H19: =BS!H23/BS!H33 -> 0.097761615 | I19: =BS!I23/BS!I33 -> 0.095386305 | ... K19: =BS!K23/BS!K33 -> 0.057723478
A20: D/A | B20: =BS!B23/BS!B18 -> 0.0066925308 | C20: =BS!C23/BS!C18 -> 0.0047635572 | D20: =BS!D23/BS!D18 -> 0.018743995 | E20: =BS!E23/BS!E18 -> 0.0083693894 | F20: =BS!F23/BS!F18 -> 0.0070432808 | G20: =BS!G23/BS!G18 -> 0.051020583 | H20: =BS!H23/BS!H18 -> 0.060698632 | I20: =BS!I23/BS!I18 -> 0.066603135 | ... K20: =BS!K23/BS!K18 -> 0.040482574
A21: Interest Coverage Ratio | B21: =IS!B15/IS!B16 -> 70.146987 | C21: =IS!C15/IS!C16 -> 100.93489 | D21: =IS!D15/IS!D16 -> 96.273072 | E21: =IS!E15/IS!E16 -> 119.44944 | F21: =IS!F15/IS!F16 -> 160.76812 | G21: =IS!G15/IS!G16 -> 73.54023 | H21: =IS!H15/IS!H16 -> 28.683168 | I21: =IS!I15/IS!I16 -> 32.023483 | ... K21: =IS!K15/IS!K16 -> 56.206799
A23: Activity Ratios | B23: FY 2014 | C23: FY 2015 | D23: FY 2016 | E23: FY 2017 | F23: FY 2018 | G23: FY 2019 | H23: FY 2020 | I23: FY 2021 | J23: FY 2022 | K23: FY 2023
A24: Asset Turnover Ratio | C24: =IS!C6/AVERAGE(BS!B18:C18) -> 1.1603235 | D24: =IS!D6/AVERAGE(BS!C18:D18) -> 0.85826142 | E24: =IS!E6/AVERAGE(BS!D18:E18) -> 1.1431613 | F24: =IS!F6/AVERAGE(BS!E18:F18) -> 1.1050335 | G24: =IS!G6/AVERAGE(BS!F18:G18) -> 1.154244 | H24: =IS!H6/AVERAGE(BS!G18:H18) -> 1.0096481 | I24: =IS!I6/AVERAGE(BS!H18:I18) -> 0.90374617 | J24: =IS!J6/AVERAGE(BS!I18:J18) -> 0.99124411 | K24: =IS!K6/AVERAGE(BS!J18:K18) -> 1.1287636
A25: Receivables Turnover Ratio | C25: =IS!C6/AVERAGE(BS!B7:C7) -> 6.192462 | D25: =IS!D6/AVERAGE(BS!C7:D7) -> 4.48909 | E25: =IS!E6/AVERAGE(BS!D7:E7) -> 6.0719729 | F25: =IS!F6/AVERAGE(BS!E7:F7) -> 5.7746934 | G25: =IS!G6/AVERAGE(BS!F7:G7) -> 5.7502928 | H25: =IS!H6/AVERAGE(BS!G7:H7) -> 5.5165073 | I25: =IS!I6/AVERAGE(BS!H7:I7) -> 4.8209502 | J25: =IS!J6/AVERAGE(BS!I7:J7) -> 4.5406849 | K25: =IS!K6/AVERAGE(BS!J7:K7) -> 4.4530394
A26: Inventory Turnover Ratio | C26: =(IS!C8+IS!C12)/AVERAGE(BS!B8:C8) -> 52.760959 | D26: =(IS!D8+IS!D12)/AVERAGE(BS!C8:D8) -> 32.519557 | E26: =(IS!E8+IS!E12)/AVERAGE(BS!D8:E8) -> 40.789668 | F26: =(IS!F8+IS!F12)/AVERAGE(BS!E8:F8) -> 51.209821 | G26: =(IS!G8+IS!G12)/AVERAGE(BS!F8:G8) -> 101.61977 | H26: =(IS!H8+IS!H12)/AVERAGE(BS!G8:H8) -> 165.65934 | I26: =(IS!I8+IS!I12)/AVERAGE(BS!H8:I8) -> 156.99459 | J26: =(IS!J8+IS!J12)/AVERAGE(BS!I8:J8) -> 132.03922 | K26: =(IS!K8+IS!K12)/AVERAGE(BS!J8:K8) -> 105.56812
A27: Payables Turnover Ratio | C27: =(IS!C8+IS!C12)/AVERAGE(BS!B19:C19) -> 5.5231798 | D27: =(IS!D8+IS!D12)/AVERAGE(BS!C19:D19) -> 5.1077769 | E27: =(IS!E8+IS!E12)/AVERAGE(BS!D19:E19) -> 5.3369032 | F27: =(IS!F8+IS!F12)/AVERAGE(BS!E19:F19) -> 4.7264112 | G27: =(IS!G8+IS!G12)/AVERAGE(BS!F19:G19) -> 6.7575221 | H27: =(IS!H8+IS!H12)/AVERAGE(BS!G19:H19) -> 8.016485 | I27: =(IS!I8+IS!I12)/AVERAGE(BS!H19:I19) -> 3.6773867 | J27: =(IS!J8+IS!J12)/AVERAGE(BS!I19:J19) -> 2.5915948 | K27: =(IS!K8+IS!K12)/AVERAGE(BS!J19:K19) -> 2.9809814
A28: Receivable Days (DSO) | C28: =365/C25 -> 58.942631 | D28: =365/D25 -> 81.308239 | E28: =365/E25 -> 60.112258 | F28: =365/F25 -> 63.206819 | G28: =365/G25 -> 63.475029 | H28: =365/H25 -> 66.165053 | I28: =365/I25 -> 75.711215 | J28: =365/J25 -> 80.384349 | K28: =365/K25 -> 81.966488
A29: Inventory Days (DIH) | C29: =365/C26 -> 6.9179941 | D29: =365/D26 -> 11.224015 | E29: =365/E26 -> 8.9483444 | F29: =365/F26 -> 7.127539 | G29: =365/G26 -> 3.5918207 | H29: =365/H26 -> 2.2033167 | I29: =365/I26 -> 2.3249208 | J29: =365/J26 -> 2.7643303 | K29: =365/K26 -> 3.4574831
A30: Payable Days | C30: =365/C27 -> 66.08512 | D30: =365/D27 -> 71.45966 | E30: =365/E27 -> 68.391722 | F30: =365/F27 -> 77.225612 | G30: =365/G27 -> 54.013882 | H30: =365/H27 -> 45.531177 | I30: =365/I27 -> 99.255268 | J30: =365/J27 -> 140.83992 | K30: =365/K27 -> 122.4429
A32: Operating Cycle | C32: =C28+C29 -> 65.860625 | D32: =D28+D29 -> 92.532254 | E32: =E28+E29 -> 69.060602 | F32: =F28+F29 -> 70.334358 | G32: =G28+G29 -> 67.066849 | H32: =H28+H29 -> 68.36837 | I32: =I28+I29 -> 78.036136 | J32: =J28+J29 -> 83.14868 | K32: =K28+K29 -> 85.423971
A33: Net Operating Cycle (CCC) | C33: =C28+C29-C30 -> -0.22449533 | D33: =D28+D29-D30 -> 21.072594 | E33: =E28+E29-E30 -> 0.66888019 | F33: =F28+F29-F30 -> -6.8912547 | G33: =G28+G29-G30 -> 13.052968 | H33: =H28+H29-H30 -> 22.837192 | I33: =I28+I29-I30 -> -21.219132 | J33: =J28+J29-J30 -> -57.691237 | K33: =K28+K29-K30 -> -37.018926
