Workbook

Sheet Cross Section Analysis
A1: Comparison of TCS, Infosys and HCL | B1: FY 2014 | C1: FY 2015 | D1: FY 2016 | E1: FY 2017 | F1: FY 2018 | G1: FY 2019 | H1: FY 2020 | I1: FY 2021 | J1: FY 2022 | K1: FY 2023
A2: EBITDA Margin
A3: TCS | B3: ='Ratio Analysis - TCS'!B3 -> 0.32103993 | C3: ='Ratio Analysis - TCS'!C3 -> 0.28669232 | D3: ='Ratio Analysis - TCS'!D3 -> 0.30216594 | E3: ='Ratio Analysis - TCS'!E3 -> 0.29898434 | F3: ='Ratio Analysis - TCS'!F3 -> 0.28527922 | G3: ='Ratio Analysis - TCS'!G3 -> 0.29061377 | H3: ='Ratio Analysis - TCS'!H3 -> 0.28909689 | I3: ='Ratio Analysis - TCS'!I3 -> 0.2896522 | ... K3: ='Ratio Analysis - TCS'!K3 -> 0.27394531
A4: INFY | B4: ='Ratio Analysis - INFY'!B3 -> 0.30407031 | C4: ='Ratio Analysis - INFY'!C3 -> 0.32270172 | D4: ='Ratio Analysis - INFY'!D3 -> 0.30809475 | E4: ='Ratio Analysis - INFY'!E3 -> 0.3027092 | F4: ='Ratio Analysis - INFY'!F3 -> 0.29977111 | G4: ='Ratio Analysis - INFY'!G3 -> 0.26943441 | H4: ='Ratio Analysis - INFY'!H3 -> 0.26785905 | I4: ='Ratio Analysis - INFY'!I3 -> 0.29306634 | ... K4: ='Ratio Analysis - INFY'!K3 -> 0.25310434
A5: HCL | B5: ='Ratio Analysis - HCL'!B3 -> 0.26546035 | C5: ='Ratio Analysis - HCL'!C3 -> 0.25401341 | D5: ='Ratio Analysis - HCL'!D3 -> 0.23508857 | E5: ='Ratio Analysis - HCL'!E3 -> 0.23557346 | F5: ='Ratio Analysis - HCL'!F3 -> 0.24085407 | G5: ='Ratio Analysis - HCL'!G3 -> 0.2422845 | H5: ='Ratio Analysis - HCL'!H3 -> 0.25124535 | I5: ='Ratio Analysis - HCL'!I3 -> 0.27488009 | ... K5: ='Ratio Analysis - HCL'!K3 -> 0.23329508
A7: PAT Margin
A8: TCS | B8: ='Ratio Analysis - TCS'!B6 -> 0.22965567 | C8: ='Ratio Analysis - TCS'!C6 -> 0.20181528 | D8: ='Ratio Analysis - TCS'!D6 -> 0.21722008 | E8: ='Ratio Analysis - TCS'!E6 -> 0.21515382 | F8: ='Ratio Analysis - TCS'!F6 -> 0.20376185 | G8: ='Ratio Analysis - TCS'!G6 -> 0.20873625 | H8: ='Ratio Analysis - TCS'!H6 -> 0.20019685 | I8: ='Ratio Analysis - TCS'!I6 -> 0.19383065 | ... K8: ='Ratio Analysis - TCS'!K6 -> 0.18412281
A9: INFY | B9: ='Ratio Analysis - INFY'!B6 -> 0.20182965 | C9: ='Ratio Analysis - INFY'!C6 -> 0.21801265 | D9: ='Ratio Analysis - INFY'!D6 -> 0.20574732 | E9: ='Ratio Analysis - INFY'!E6 -> 0.20064585 | F9: ='Ratio Analysis - INFY'!F6 -> 0.21709805 | G9: ='Ratio Analysis - INFY'!G6 -> 0.18004371 | H9: ='Ratio Analysis - INFY'!H6 -> 0.17729769 | I9: ='Ratio Analysis - INFY'!I6 -> 0.18847214 | ... K9: ='Ratio Analysis - INFY'!K6 -> 0.16120507
A10: HCL | B10: ='Ratio Analysis - HCL'!B6 -> 0.19833333 | C10: ='Ratio Analysis - HCL'!C6 -> 0.19336518 | D10: ='Ratio Analysis - HCL'!D6 -> 0.17503858 | E10: ='Ratio Analysis - HCL'!E6 -> 0.17692165 | F10: ='Ratio Analysis - HCL'!F6 -> 0.16836232 | G10: ='Ratio Analysis - HCL'!G6 -> 0.16490142 | H10: ='Ratio Analysis - HCL'!H6 -> 0.1551533 | I10: ='Ratio Analysis - HCL'!I6 -> 0.14605667 | ... K10: ='Ratio Analysis - HCL'!K6 -> 0.14444531
A12: ROE
A13: TCS | C13: ='Ratio Analysis - TCS'!C8 -> 0.39054005 | D13: ='Ratio Analysis - TCS'!D8 -> 0.39402702 | E13: ='Ratio Analysis - TCS'!E8 -> 0.33275741 | F13: ='Ratio Analysis - TCS'!F8 -> 0.30011039 | G13: ='Ratio Analysis - TCS'!G8 -> 0.35880043 | H13: ='Ratio Analysis - TCS'!H8 -> 0.37034492 | I13: ='Ratio Analysis - TCS'!I8 -> 0.3774068 | J13: ='Ratio Analysis - TCS'!J8 -> 0.43318603 | K13: ='Ratio Analysis - TCS'!K8 -> 0.46557895
A14: INFY | C14: ='Ratio Analysis - INFY'!C8 -> 0.2597359 | D14: ='Ratio Analysis - INFY'!D8 -> 0.23984708 | E14: ='Ratio Analysis - INFY'!E8 -> 0.21958906 | F14: ='Ratio Analysis - INFY'!F8 -> 0.23940675 | G14: ='Ratio Analysis - INFY'!G8 -> 0.23711229 | H14: ='Ratio Analysis - INFY'!H8 -> 0.25363393 | I14: ='Ratio Analysis - INFY'!I8 -> 0.27135305 | J14: ='Ratio Analysis - INFY'!J8 -> 0.28993299 | K14: ='Ratio Analysis - INFY'!K8 -> 0.31802074
A15: HCL | C15: ='Ratio Analysis - HCL'!C8 -> 0.33324786 | D15: ='Ratio Analysis - HCL'!D8 -> 0.21586019 | E15: ='Ratio Analysis - HCL'!E8 -> 0.28344907 | F15: ='Ratio Analysis - HCL'!F8 -> 0.25093514 | G15: ='Ratio Analysis - HCL'!G8 -> 0.25997046 | H15: ='Ratio Analysis - HCL'!H8 -> 0.23806653 | I15: ='Ratio Analysis - HCL'!I8 -> 0.19990494 | J15: ='Ratio Analysis - HCL'!J8 -> 0.22113557 | K15: ='Ratio Analysis - HCL'!K8 -> 0.2331324
A17: Cash Ratio
A18: TCS | B18: ='Ratio Analysis - TCS'!B14 -> 0.99553295 | C18: ='Ratio Analysis - TCS'!C14 -> 0.98673113 | D18: ='Ratio Analysis - TCS'!D14 -> 1.8798253 | E18: ='Ratio Analysis - TCS'!E14 -> 3.1549752 | F18: ='Ratio Analysis - TCS'!F14 -> 2.4045322 | G18: ='Ratio Analysis - TCS'!G14 -> 1.8990672 | H18: ='Ratio Analysis - TCS'!H14 -> 1.3232077 | I18: ='Ratio Analysis - TCS'!I14 -> 1.1268921 | ... K18: ='Ratio Analysis - TCS'!K14 -> 1.100349
A19: INFY | B19: ='Ratio Analysis - INFY'!B14 -> 2.4082786 | C19: ='Ratio Analysis - INFY'!C14 -> 2.0150293 | D19: ='Ratio Analysis - INFY'!D14 -> 2.4754136 | E19: ='Ratio Analysis - INFY'!E14 -> 2.3260544 | F19: ='Ratio Analysis - INFY'!F14 -> 1.8592698 | G19: ='Ratio Analysis - INFY'!G14 -> 1.405462 | H19: ='Ratio Analysis - INFY'!H14 -> 1.1173763 | I19: ='Ratio Analysis - INFY'!I14 -> 1.1337105 | ... K19: ='Ratio Analysis - INFY'!K14 -> 0.48695963
A20: HCL | B20: ='Ratio Analysis - HCL'!B14 -> 1.1800397 | C20: ='Ratio Analysis - HCL'!C14 -> 1.2358604 | D20: ='Ratio Analysis - HCL'!D14 -> 1.1544314 | E20: ='Ratio Analysis - HCL'!E14 -> 1.2013676 | F20: ='Ratio Analysis - HCL'!F14 -> 0.78645448 | G20: ='Ratio Analysis - HCL'!G14 -> 0.97554374 | H20: ='Ratio Analysis - HCL'!H14 -> 0.54577384 | I20: ='Ratio Analysis - HCL'!I14 -> 1.3869111 | ... K20: ='Ratio Analysis - HCL'!K14 -> 1.3814922
A22: A/E Ratio
A23: TCS | B23: ='Ratio Analysis - TCS'!B18 -> 1.3391843 | C23: ='Ratio Analysis - TCS'!C18 -> 1.4164287 | D23: ='Ratio Analysis - TCS'!D18 -> 1.2361012 | E23: ='Ratio Analysis - TCS'!E18 -> 1.1819473 | F23: ='Ratio Analysis - TCS'!F18 -> 1.2291126 | G23: ='Ratio Analysis - TCS'!G18 -> 1.2669885 | H23: ='Ratio Analysis - TCS'!H18 -> 1.4173619 | I23: ='Ratio Analysis - TCS'!I18 -> 1.4923084 | ... K23: ='Ratio Analysis - TCS'!K18 -> 1.5663334
A24: INFY | B24: ='Ratio Analysis - INFY'!B18 -> 1.2792724 | C24: ='Ratio Analysis - INFY'!C18 -> 1.3065476 | D24: ='Ratio Analysis - INFY'!D18 -> 1.2162801 | E24: ='Ratio Analysis - INFY'!E18 -> 1.2053579 | F24: ='Ratio Analysis - INFY'!F18 -> 1.2221829 | G24: ='Ratio Analysis - INFY'!G18 -> 1.2932037 | H24: ='Ratio Analysis - INFY'!H18 -> 1.3942045 | I24: ='Ratio Analysis - INFY'!I18 -> 1.400211 | ... K24: ='Ratio Analysis - INFY'!K18 -> 1.6438551
A25: HCL | B25: ='Ratio Analysis - HCL'!B18 -> 1.5290175 | C25: ='Ratio Analysis - HCL'!C18 -> 1.4500089 | D25: ='Ratio Analysis - HCL'!D18 -> 1.4253102 | E25: ='Ratio Analysis - HCL'!E18 -> 1.3816195 | F25: ='Ratio Analysis - HCL'!F18 -> 1.3188864 | G25: ='Ratio Analysis - HCL'!G18 -> 1.4070511 | H25: ='Ratio Analysis - HCL'!H18 -> 1.6106066 | I25: ='Ratio Analysis - HCL'!I18 -> 1.4321594 | ... K25: ='Ratio Analysis - HCL'!K18 -> 1.4258846
A27: Asset Turnover Ratio
A28: TCS | C28: ='Ratio Analysis - TCS'!C24 -> 1.4037852 | D28: ='Ratio Analysis - TCS'!D24 -> 1.3827207 | E28: ='Ratio Analysis - TCS'!E24 -> 1.2819687 | F28: ='Ratio Analysis - TCS'!F24 -> 1.2218896 | G28: ='Ratio Analysis - TCS'!G24 -> 1.3767618 | H28: ='Ratio Analysis - TCS'!H24 -> 1.3805684 | I28: ='Ratio Analysis - TCS'!I24 -> 1.3378886 | J28: ='Ratio Analysis - TCS'!J24 -> 1.4452598 | K28: ='Ratio Analysis - TCS'!K24 -> 1.6132538
A29: INFY | C29: ='Ratio Analysis - INFY'!C24 -> 0.92083891 | D29: ='Ratio Analysis - INFY'!D24 -> 0.92739785 | E29: ='Ratio Analysis - INFY'!E24 -> 0.90408604 | F29: ='Ratio Analysis - INFY'!F24 -> 0.90873062 | G29: ='Ratio Analysis - INFY'!G24 -> 1.0471132 | H29: ='Ratio Analysis - INFY'!H24 -> 1.0643786 | I29: ='Ratio Analysis - INFY'!I24 -> 1.0302793 | J29: ='Ratio Analysis - INFY'!J24 -> 1.1053871 | K29: ='Ratio Analysis - INFY'!K24 -> 1.2387279
A30: HCL | C30: ='Ratio Analysis - HCL'!C24 -> 1.1603235 | D30: ='Ratio Analysis - HCL'!D24 -> 0.85826142 | E30: ='Ratio Analysis - HCL'!E24 -> 1.1431613 | F30: ='Ratio Analysis - HCL'!F24 -> 1.1050335 | G30: ='Ratio Analysis - HCL'!G24 -> 1.154244 | H30: ='Ratio Analysis - HCL'!H24 -> 1.0096481 | I30: ='Ratio Analysis - HCL'!I24 -> 0.90374617 | J30: ='Ratio Analysis - HCL'!J24 -> 0.99124411 | K30: ='Ratio Analysis - HCL'!K24 -> 1.1287636
A32: Net Operating Cycle
A33: TCS | C33: ='Ratio Analysis - TCS'!C33 -> -34.473416 | D33: ='Ratio Analysis - TCS'!D33 -> -368.70776 | E33: ='Ratio Analysis - TCS'!E33 -> -241.36341 | F33: ='Ratio Analysis - TCS'!F33 -> -191.05747 | G33: ='Ratio Analysis - TCS'!G33 -> -197.93938 | H33: ='Ratio Analysis - TCS'!H33 -> -236.31282 | I33: ='Ratio Analysis - TCS'!I33 -> -258.29376 | J33: ='Ratio Analysis - TCS'!J33 -> -324.01996 | K33: ='Ratio Analysis - TCS'!K33 -> -300.92347
A34: INFY | C34: ='Ratio Analysis - INFY'!C33 -> 46.715583 | D34: ='Ratio Analysis - INFY'!D33 -> 40.962222 | E34: ='Ratio Analysis - INFY'!E33 -> 38.586829 | F34: ='Ratio Analysis - INFY'!F33 -> 34.128384 | G34: ='Ratio Analysis - INFY'!G33 -> 8.7879439 | H34: ='Ratio Analysis - INFY'!H33 -> -17.951049 | I34: ='Ratio Analysis - INFY'!I33 -> -14.749254 | J34: ='Ratio Analysis - INFY'!J33 -> -1.8756261 | K34: ='Ratio Analysis - INFY'!K33 -> -1.0366044
A35: HCL | C35: ='Ratio Analysis - HCL'!C33 -> -0.22449533 | D35: ='Ratio Analysis - HCL'!D33 -> 21.072594 | E35: ='Ratio Analysis - HCL'!E33 -> 0.66888019 | F35: ='Ratio Analysis - HCL'!F33 -> -6.8912547 | G35: ='Ratio Analysis - HCL'!G33 -> 13.052968 | H35: ='Ratio Analysis - HCL'!H33 -> 22.837192 | I35: ='Ratio Analysis - HCL'!I33 -> -21.219132 | J35: ='Ratio Analysis - HCL'!J33 -> -57.691237 | K35: ='Ratio Analysis - HCL'!K33 -> -37.018926

Sheet Ratio Analysis - TCS
A2: Profitability Ratios | B2: FY 2014 | C2: FY 2015 | D2: FY 2016 | E2: FY 2017 | F2: FY 2018 | G2: FY 2019 | H2: FY 2020 | I2: FY 2021 | J2: FY 2022 | K2: FY 2023
A3: EBITDA Margin | B3: =[1]IS!B42 -> 0.32103993 | C3: =[1]IS!C42 -> 0.28669232 | D3: =[1]IS!D42 -> 0.30216594 | E3: =[1]IS!E42 -> 0.29898434 | F3: =[1]IS!F42 -> 0.28527922 | G3: =[1]IS!G42 -> 0.29061377 | H3: =[1]IS!H42 -> 0.28909689 | I3: =[1]IS!I42 -> 0.2896522 | ... K3: =[1]IS!K42 -> 0.27394531
A4: EBIT Margin | B4: =[1]IS!B43 -> 0.30487201 | C4: =[1]IS!C43 -> 0.26840701 | D4: =[1]IS!D43 -> 0.28526806 | E4: =[1]IS!E43 -> 0.28272238 | F4: =[1]IS!F43 -> 0.26938917 | G4: =[1]IS!G43 -> 0.27697746 | H4: =[1]IS!H43 -> 0.26725104 | I4: =[1]IS!I43 -> 0.26535613 | ... K4: =[1]IS!K43 -> 0.25200627
A5: EBT Margin | B5: =[1]IS!B44 -> 0.30441039 | C5: =[1]IS!C44 -> 0.26734783 | D5: =[1]IS!D44 -> 0.2849727 | E5: =[1]IS!E44 -> 0.28246049 | F5: =[1]IS!F44 -> 0.2689789 | G5: =[1]IS!G44 -> 0.27566424 | H5: =[1]IS!H44 -> 0.26153113 | I5: =[1]IS!I44 -> 0.26154885 | ... K5: =[1]IS!K44 -> 0.24860314
A6: PAT Margin | B6: =[1]IS!B45 -> 0.22965567 | C6: =[1]IS!C45 -> 0.20181528 | D6: =[1]IS!D45 -> 0.21722008 | E6: =[1]IS!E45 -> 0.21515382 | F6: =[1]IS!F45 -> 0.20376185 | G6: =[1]IS!G45 -> 0.20873625 | H6: =[1]IS!H45 -> 0.20019685 | I6: =[1]IS!I45 -> 0.19383065 | ... K6: =[1]IS!K45 -> 0.18412281
A7: ROA | C7: =[1]IS!C20/AVERAGE([1]BS!B22:C22) -> 0.2833053 | D7: =[1]IS!D20/AVERAGE([1]BS!C22:D22) -> 0.30035471 | E7: =[1]IS!E20/AVERAGE([1]BS!D22:E22) -> 0.27582046 | F7: =[1]IS!F20/AVERAGE([1]BS!E22:F22) -> 0.2489745 | G7: =[1]IS!G20/AVERAGE([1]BS!F22:G22) -> 0.28738009 | H7: =[1]IS!H20/AVERAGE([1]BS!G22:H22) -> 0.27638545 | I7: =[1]IS!I20/AVERAGE([1]BS!H22:I22) -> 0.25932382 | J7: =[1]IS!J20/AVERAGE([1]BS!I22:J22) -> 0.28294379 | K7: =[1]IS!K20/AVERAGE([1]BS!J22:K22) -> 0.29703682
A8: ROE | C8: =[1]IS!C20/AVERAGE([1]BS!B38:C38) -> 0.39054005 | D8: =[1]IS!D20/AVERAGE([1]BS!C38:D38) -> 0.39402702 | E8: =[1]IS!E20/AVERAGE([1]BS!D38:E38) -> 0.33275741 | F8: =[1]IS!F20/AVERAGE([1]BS!E38:F38) -> 0.30011039 | G8: =[1]IS!G20/AVERAGE([1]BS!F38:G38) -> 0.35880043 | H8: =[1]IS!H20/AVERAGE([1]BS!G38:H38) -> 0.37034492 | I8: =[1]IS!I20/AVERAGE([1]BS!H38:I38) -> 0.3774068 | J8: =[1]IS!J20/AVERAGE([1]BS!I38:J38) -> 0.43318603 | K8: =[1]IS!K20/AVERAGE([1]BS!J38:K38) -> 0.46557895
A9: ROCE | C9: =[1]IS!C16/(AVERAGE([1]BS!B38:C38)+AVERAGE([1]BS!B28:C28)) -> 0.51817308 | D9: =[1]IS!D16/(AVERAGE([1]BS!C38:D38)+AVERAGE([1]BS!C28:D28)) -> 0.51663553 | E9: =[1]IS!E16/(AVERAGE([1]BS!D38:E38)+AVERAGE([1]BS!D28:E28)) -> 0.43683335 | F9: =[1]IS!F16/(AVERAGE([1]BS!E38:F38)+AVERAGE([1]BS!E28:F28)) -> 0.39648155 | G9: =[1]IS!G16/(AVERAGE([1]BS!F38:G38)+AVERAGE([1]BS!F28:G28)) -> 0.47583563 | H9: =[1]IS!H16/(AVERAGE([1]BS!G38:H38)+AVERAGE([1]BS!G28:H28)) -> 0.47546779 | I9: =[1]IS!I16/(AVERAGE([1]BS!H38:I38)+AVERAGE([1]BS!H28:I28)) -> 0.47927844 | J9: =[1]IS!J16/(AVERAGE([1]BS!I38:J38)+AVERAGE([1]BS!I28:J28)) -> 0.55283551 | K9: =[1]IS!K16/(AVERAGE([1]BS!J38:K38)+AVERAGE([1]BS!J28:K28)) -> 0.59585896
A11: Liquidity Ratios | B11: FY 2014 | C11: FY 2015 | D11: FY 2016 | E11: FY 2017 | F11: FY 2018 | G11: FY 2019 | H11: FY 2020 | I11: FY 2021 | J11: FY 2022 | K11: FY 2023
A12: Current Ratio | B12: =[1]BS!B79 -> 2.7375138 | C12: =[1]BS!C79 -> 2.4024227 | D12: =[1]BS!D79 -> 4.0601837 | E12: =[1]BS!E79 -> 5.5344542 | F12: =[1]BS!F79 -> 4.5559794 | G12: =[1]BS!G79 -> 4.1718439 | H12: =[1]BS!H79 -> 3.3347007 | I12: =[1]BS!I79 -> 2.9067486 | ... K12: =[1]BS!K79 -> 2.5315671
A13: Quick Ratio | B13: =[1]BS!B80 -> 2.158905 | C13: =[1]BS!C80 -> 1.9926224 | D13: =[1]BS!D80 -> 3.4260389 | E13: =[1]BS!E80 -> 4.7134785 | F13: =[1]BS!F80 -> 3.8036235 | G13: =[1]BS!G80 -> 3.1373393 | H13: =[1]BS!H80 -> 2.4515152 | I13: =[1]BS!I80 -> 2.0075538 | ... K13: =[1]BS!K80 -> 2.2471877
A14: Cash Ratio | B14: =[1]BS!B81 -> 0.99553295 | C14: =[1]BS!C81 -> 0.98673113 | D14: =[1]BS!D81 -> 1.8798253 | E14: =[1]BS!E81 -> 3.1549752 | F14: =[1]BS!F81 -> 2.4045322 | G14: =[1]BS!G81 -> 1.8990672 | H14: =[1]BS!H81 -> 1.3232077 | I14: =[1]BS!I81 -> 1.1268921 | ... K14: =[1]BS!K81 -> 1.100349
A15: Defensive Interval | B15: =[1]BS!B12/(SUM([1]IS!B8:B12)/365) -> 276.36083 | C15: =[1]BS!C12/(SUM([1]IS!C8:C12)/365) -> 253.92024 | D15: =[1]BS!D12/(SUM([1]IS!D8:D12)/365) -> 295.92203 | E15: =[1]BS!E12/(SUM([1]IS!E8:E12)/365) -> 342.24902 | F15: =[1]BS!F12/(SUM([1]IS!F8:F12)/365) -> 327.27028 | G15: =[1]BS!G12/(SUM([1]IS!G8:G12)/365) -> 314.40499 | H15: =[1]BS!H12/(SUM([1]IS!H8:H12)/365) -> 286.80342 | I15: =[1]BS!I12/(SUM([1]IS!I8:I12)/365) -> 304.90118 | ... K15: =[1]BS!K12/(SUM([1]IS!K8:K12)/365) -> 242.17083
A17: Solvency Ratios | B17: FY 2014 | C17: FY 2015 | D17: FY 2016 | E17: FY 2017 | F17: FY 2018 | G17: FY 2019 | H17: FY 2020 | I17: FY 2021 | J17: FY 2022 | K17: FY 2023
A18: A/E | B18: =[1]BS!B83 -> 1.3391843 | C18: =[1]BS!C83 -> 1.4164287 | D18: =[1]BS!D83 -> 1.2361012 | E18: =[1]BS!E83 -> 1.1819473 | F18: =[1]BS!F83 -> 1.2291126 | G18: =[1]BS!G83 -> 1.2669885 | H18: =[1]BS!H83 -> 1.4173619 | I18: =[1]BS!I83 -> 1.4923084 | ... K18: =[1]BS!K83 -> 1.5663334
A19: D/E | B19: =[1]BS!B84 -> 0.0025501601 | C19: =[1]BS!C84 -> 0.0022075819 | D19: =[1]BS!D84 -> 0.0011620256 | E19: =[1]BS!E84 -> 0.00082005082 | F19: =[1]BS!F84 -> 0.00063135742 | G19: =[1]BS!G84 -> 0.00048943815 | H19: =[1]BS!H84 -> 0.081487687 | I19: =[1]BS!I84 -> 0.074654452 | ... K19: =[1]BS!K84 -> 0.068010876
A20: D/A | B20: =[1]BS!B85 -> 0.0019042637 | C20: =[1]BS!C85 -> 0.0015585549 | D20: =[1]BS!D85 -> 0.00094007317 | E20: =[1]BS!E85 -> 0.00069381333 | F20: =[1]BS!F85 -> 0.00051366931 | G20: =[1]BS!G85 -> 0.00038630038 | H20: =[1]BS!H85 -> 0.057492507 | I20: =[1]BS!I85 -> 0.050026155 | ... K20: =[1]BS!K85 -> 0.043420436
A21: Interest Coverage Ratio | B21: =[1]IS!B16/[1]IS!B17 -> 660.446 | C21: =[1]IS!C16/[1]IS!C17 -> 253.40896 | D21: =[1]IS!D16/[1]IS!D17 -> 965.84848 | E21: =[1]IS!E16/[1]IS!E17 -> 1079.5312 | F21: =[1]IS!F16/[1]IS!F17 -> 656.61538 | G21: =[1]IS!G16/[1]IS!G17 -> 210.91414 | H21: =[1]IS!H16/[1]IS!H17 -> 46.722944 | I21: =[1]IS!I16/[1]IS!I17 -> 69.697017 | ... K21: =[1]IS!K16/[1]IS!K17 -> 74.051348
A23: Activity Ratios | B23: FY 2014 | C23: FY 2015 | D23: FY 2016 | E23: FY 2017 | F23: FY 2018 | G23: FY 2019 | H23: FY 2020 | I23: FY 2021 | J23: FY 2022 | K23: FY 2023
A24: Asset Turnover Ratio | C24: =[1]IS!C6/AVERAGE([1]BS!B22:C22) -> 1.4037852 | D24: =[1]IS!D6/AVERAGE([1]BS!C22:D22) -> 1.3827207 | E24: =[1]IS!E6/AVERAGE([1]BS!D22:E22) -> 1.2819687 | F24: =[1]IS!F6/AVERAGE([1]BS!E22:F22) -> 1.2218896 | G24: =[1]IS!G6/AVERAGE([1]BS!F22:G22) -> 1.3767618 | H24: =[1]IS!H6/AVERAGE([1]BS!G22:H22) -> 1.3805684 | I24: =[1]IS!I6/AVERAGE([1]BS!H22:I22) -> 1.3378886 | J24: =[1]IS!J6/AVERAGE([1]BS!I22:J22) -> 1.4452598 | K24: =[1]IS!K6/AVERAGE([1]BS!J22:K22) -> 1.6132538
A25: Receivables Turnover Ratio | C25: =[1]IS!C6/AVERAGE([1]BS!B8:C8) -> 5.0877834 | D25: =[1]IS!D6/AVERAGE([1]BS!C8:D8) -> 5.0203388 | E25: =[1]IS!E6/AVERAGE([1]BS!D8:E8) -> 5.2339687 | F25: =[1]IS!F6/AVERAGE([1]BS!E8:F8) -> 5.3299411 | G25: =[1]IS!G6/AVERAGE([1]BS!F8:G8) -> 5.7669491 | H25: =[1]IS!H6/AVERAGE([1]BS!G8:H8) -> 5.582121 | I25: =[1]IS!I6/AVERAGE([1]BS!H8:I8) -> 5.5208131 | J25: =[1]IS!J6/AVERAGE([1]BS!I8:J8) -> 5.4465078 | K25: =[1]IS!K6/AVERAGE([1]BS!J8:K8) -> 4.9890371
A26: Inventory Turnover Ratio | C26: =([1]IS!C8+[1]IS!C12)/AVERAGE([1]BS!B10:C10) -> 1665.5646 | D26: =([1]IS!D8+[1]IS!D12)/AVERAGE([1]BS!C10:D10) -> 438.54069 | E26: =([1]IS!E8+[1]IS!E12)/AVERAGE([1]BS!D10:E10) -> 413.08108 | F26: =([1]IS!F8+[1]IS!F12)/AVERAGE([1]BS!E10:F10) -> 314.21277 | G26: =([1]IS!G8+[1]IS!G12)/AVERAGE([1]BS!F10:G10) -> 462.44444 | H26: =([1]IS!H8+[1]IS!H12)/AVERAGE([1]BS!G10:H10) -> 1114.8 | I26: =([1]IS!I8+[1]IS!I12)/AVERAGE([1]BS!H10:I10) -> 1340.4615 | J26: =([1]IS!J8+[1]IS!J12)/AVERAGE([1]BS!I10:J10) -> 568.28571 | K26: =([1]IS!K8+[1]IS!K12)/AVERAGE([1]BS!J10:K10) -> 406.83333
A27: Payables Turnover Ratio | C27: =([1]IS!C8+[1]IS!C12)/AVERAGE([1]BS!B23:C23) -> 3.4293863 | D27: =([1]IS!D8+[1]IS!D12)/AVERAGE([1]BS!C23:D23) -> 0.82533564 | E27: =([1]IS!E8+[1]IS!E12)/AVERAGE([1]BS!D23:E23) -> 1.1699326 | F27: =([1]IS!F8+[1]IS!F12)/AVERAGE([1]BS!E23:F23) -> 1.4000758 | G27: =([1]IS!G8+[1]IS!G12)/AVERAGE([1]BS!F23:G23) -> 1.3930215 | H27: =([1]IS!H8+[1]IS!H12)/AVERAGE([1]BS!G23:H23) -> 1.208499 | I27: =([1]IS!I8+[1]IS!I12)/AVERAGE([1]BS!H23:I23) -> 1.1241855 | J27: =([1]IS!J8+[1]IS!J12)/AVERAGE([1]BS!I23:J23) -> 0.93188873 | K27: =([1]IS!K8+[1]IS!K12)/AVERAGE([1]BS!J23:K23) -> 0.97338251
A28: Receivable Days (DSO) | C28: =365/C25 -> 71.740475 | D28: =365/D25 -> 72.704256 | E28: =365/E25 -> 69.736756 | F28: =365/F25 -> 68.481057 | G28: =365/G25 -> 63.291698 | H28: =365/H25 -> 65.387332 | I28: =365/I25 -> 66.11345 | J28: =365/J25 -> 67.015418 | K28: =365/K25 -> 73.16041
A29: Inventory Days (DIH) | C29: =365/C26 -> 0.21914491 | D29: =365/D26 -> 0.83230589 | E29: =365/E26 -> 0.88360377 | F29: =365/F26 -> 1.1616333 | G29: =365/G26 -> 0.789284 | H29: =365/H26 -> 0.32741299 | I29: =365/I26 -> 0.27229427 | J29: =365/J26 -> 0.64228255 | K29: =365/K26 -> 0.89717329
A30: Payable Days | C30: =365/C27 -> 106.43304 | D30: =365/D27 -> 442.24432 | E30: =365/E27 -> 311.98377 | F30: =365/F27 -> 260.70016 | G30: =365/G27 -> 262.02036 | H30: =365/H27 -> 302.02757 | I30: =365/I27 -> 324.6795 | J30: =365/J27 -> 391.67766 | K30: =365/K27 -> 374.98105
A32: Operating Cycle | C32: =C28+C29 -> 71.95962 | D32: =D28+D29 -> 73.536562 | E32: =E28+E29 -> 70.62036 | F32: =F28+F29 -> 69.64269 | G32: =G28+G29 -> 64.080982 | H32: =H28+H29 -> 65.714745 | I32: =I28+I29 -> 66.385745 | J32: =J28+J29 -> 67.657701 | K32: =K28+K29 -> 74.057583
A33: Net Operating Cycle (CCC) | C33: =C28+C29-C30 -> -34.473416 | D33: =D28+D29-D30 -> -368.70776 | E33: =E28+E29-E30 -> -241.36341 | F33: =F28+F29-F30 -> -191.05747 | G33: =G28+G29-G30 -> -197.93938 | H33: =H28+H29-H30 -> -236.31282 | I33: =I28+I29-I30 -> -258.29376 | J33: =J28+J29-J30 -> -324.01996 | K33: =K28+K29-K30 -> -300.92347

Sheet Ratio Analysis - INFY
A2: Profitability Ratios | B2: FY 2014 | C2: FY 2015 | D2: FY 2016 | E2: FY 2017 | F2: FY 2018 | G2: FY 2019 | H2: FY 2020 | I2: FY 2021 | J2: FY 2022 | K2: FY 2023
A3: EBITDA Margin | B3: =[2]IS!B12/[2]IS!B6 -> 0.30407031 | C3: =[2]IS!C12/[2]IS!C6 -> 0.32270172 | D3: =[2]IS!D12/[2]IS!D6 -> 0.30809475 | E3: =[2]IS!E12/[2]IS!E6 -> 0.3027092 | F3: =[2]IS!F12/[2]IS!F6 -> 0.29977111 | G3: =[2]IS!G12/[2]IS!G6 -> 0.26943441 | H3: =[2]IS!H12/[2]IS!H6 -> 0.26785905 | I3: =[2]IS!I12/[2]IS!I6 -> 0.29306634 | ... K3: =[2]IS!K12/[2]IS!K6 -> 0.25310434
A4: EBIT Margin | B4: =[2]IS!B14/[2]IS!B6 -> 0.27912571 | C4: =[2]IS!C14/[2]IS!C6 -> 0.3047807 | D4: =[2]IS!D14/[2]IS!D6 -> 0.28584067 | E4: =[2]IS!E14/[2]IS!E6 -> 0.27890234 | F4: =[2]IS!F14/[2]IS!F6 -> 0.27453849 | G4: =[2]IS!G14/[2]IS!G6 -> 0.24592961 | H4: =[2]IS!H14/[2]IS!H6 -> 0.23694895 | I4: =[2]IS!I14/[2]IS!I6 -> 0.26124687 | ... K4: =[2]IS!K14/[2]IS!K6 -> 0.22483742
A5: EBT Margin | B5: =[2]IS!B16/[2]IS!B6 -> 0.27895524 | C5: =[2]IS!C16/[2]IS!C6 -> 0.30456924 | D5: =[2]IS!D16/[2]IS!D6 -> 0.28584067 | E5: =[2]IS!E16/[2]IS!E6 -> 0.27890234 | F5: =[2]IS!F16/[2]IS!F6 -> 0.27453849 | G5: =[2]IS!G16/[2]IS!G6 -> 0.24592961 | H5: =[2]IS!H16/[2]IS!H6 -> 0.23513259 | I5: =[2]IS!I16/[2]IS!I6 -> 0.25934764 | ... K5: =[2]IS!K16/[2]IS!K6 -> 0.22293735
A6: PAT Margin | B6: =[2]IS!B18/[2]IS!B6 -> 0.20182965 | C6: =[2]IS!C18/[2]IS!C6 -> 0.21801265 | D6: =[2]IS!D18/[2]IS!D6 -> 0.20574732 | E6: =[2]IS!E18/[2]IS!E6 -> 0.20064585 | F6: =[2]IS!F18/[2]IS!F6 -> 0.21709805 | G6: =[2]IS!G18/[2]IS!G6 -> 0.18004371 | H6: =[2]IS!H18/[2]IS!H6 -> 0.17729769 | I6: =[2]IS!I18/[2]IS!I6 -> 0.18847214 | ... K6: =[2]IS!K18/[2]IS!K6 -> 0.16120507
A7: ROA | C7: =[2]IS!C18/AVERAGE([2]BS!B18:C18) -> 0.20075453 | D7: =[2]IS!D18/AVERAGE([2]BS!C18:D18) -> 0.19080962 | E7: =[2]IS!E18/AVERAGE([2]BS!D18:E18) -> 0.18140111 | F7: =[2]IS!F18/AVERAGE([2]BS!E18:F18) -> 0.19728364 | G7: =[2]IS!G18/AVERAGE([2]BS!F18:G18) -> 0.18852615 | H7: =[2]IS!H18/AVERAGE([2]BS!G18:H18) -> 0.18871186 | I7: =[2]IS!I18/AVERAGE([2]BS!H18:I18) -> 0.19417895 | J7: =[2]IS!J18/AVERAGE([2]BS!I18:J18) -> 0.19719943 | K7: =[2]IS!K18/AVERAGE([2]BS!J18:K18) -> 0.19968922
A8: ROE | C8: =[2]IS!C18/AVERAGE([2]BS!B33:C33) -> 0.2597359 | D8: =[2]IS!D18/AVERAGE([2]BS!C33:D33) -> 0.23984708 | E8: =[2]IS!E18/AVERAGE([2]BS!D33:E33) -> 0.21958906 | F8: =[2]IS!F18/AVERAGE([2]BS!E33:F33) -> 0.23940675 | G8: =[2]IS!G18/AVERAGE([2]BS!F33:G33) -> 0.23711229 | H8: =[2]IS!H18/AVERAGE([2]BS!G33:H33) -> 0.25363393 | I8: =[2]IS!I18/AVERAGE([2]BS!H33:I33) -> 0.27135305 | J8: =[2]IS!J18/AVERAGE([2]BS!I33:J33) -> 0.28993299 | K8: =[2]IS!K18/AVERAGE([2]BS!J33:K33) -> 0.31802074
A9: ROCE | C9: =[2]IS!B14/(AVERAGE([2]BS!B33:C33)+AVERAGE([2]BS!B23:C23)) -> 0.30938635 | D9: =[2]IS!C14/(AVERAGE([2]BS!C33:D33)+AVERAGE([2]BS!C23:D23)) -> 0.30753912 | E9: =[2]IS!D14/(AVERAGE([2]BS!D33:E33)+AVERAGE([2]BS!D23:E23)) -> 0.28670655 | F9: =[2]IS!E14/(AVERAGE([2]BS!E33:F33)+AVERAGE([2]BS!E23:F23)) -> 0.29798515 | G9: =[2]IS!F14/(AVERAGE([2]BS!F33:G33)+AVERAGE([2]BS!F23:G23)) -> 0.31201416 | H9: =[2]IS!G14/(AVERAGE([2]BS!G33:H33)+AVERAGE([2]BS!G23:H23)) -> 0.31203286 | I9: =[2]IS!H14/(AVERAGE([2]BS!H33:I33)+AVERAGE([2]BS!H23:I23)) -> 0.29329419 | J9: =[2]IS!I14/(AVERAGE([2]BS!I33:J33)+AVERAGE([2]BS!I23:J23)) -> 0.33174816 | K9: =[2]IS!J14/(AVERAGE([2]BS!J33:K33)+AVERAGE([2]BS!J23:K23)) -> 0.37146884
A11: Liquidity Ratios | B11: FY 2014 | C11: FY 2015 | D11: FY 2016 | E11: FY 2017 | F11: FY 2018 | G11: FY 2019 | H11: FY 2020 | I11: FY 2021 | J11: FY 2022 | K11: FY 2023
A12: Current Ratio | B12: =[2]BS!B10/[2]BS!B22 -> 3.5805835 | C12: =[2]BS!C10/[2]BS!C22 -> 3.0472812 | D12: =[2]BS!D10/[2]BS!D22 -> 3.9091321 | E12: =[2]BS!E10/[2]BS!E22 -> 3.8325127 | F12: =[2]BS!F10/[2]BS!F22 -> 3.5460475 | G12: =[2]BS!G10/[2]BS!G22 -> 2.837107 | H12: =[2]BS!H10/[2]BS!H22 -> 2.6168009 | I12: =[2]BS!I10/[2]BS!I22 -> 2.5448565 | ... K12: =[2]BS!K10/[2]BS!K22 -> 1.8088348
A13: Quick Ratio | B13: =([2]BS!B6+[2]BS!B7)/[2]BS!B22 -> 3.1024021 | C13: =([2]BS!C6+[2]BS!C7)/[2]BS!C22 -> 2.6415532 | D13: =([2]BS!D6+[2]BS!D7)/[2]BS!D22 -> 3.3312184 | E13: =([2]BS!E6+[2]BS!E7)/[2]BS!E22 -> 3.2053807 | F13: =([2]BS!F6+[2]BS!F7)/[2]BS!F22 -> 2.7909961 | G13: =([2]BS!G6+[2]BS!G7)/[2]BS!G22 -> 2.2009872 | H13: =([2]BS!H6+[2]BS!H7)/[2]BS!H22 -> 2.0037879 | I13: =([2]BS!I6+[2]BS!I7)/[2]BS!I22 -> 1.9421747 | ... K13: =([2]BS!K6+[2]BS!K7)/[2]BS!K22 -> 1.1357628
A14: Cash Ratio | B14: =[2]BS!B6/[2]BS!B22 -> 2.4082786 | C14: =[2]BS!C6/[2]BS!C22 -> 2.0150293 | D14: =[2]BS!D6/[2]BS!D22 -> 2.4754136 | E14: =[2]BS!E6/[2]BS!E22 -> 2.3260544 | F14: =[2]BS!F6/[2]BS!F22 -> 1.8592698 | G14: =[2]BS!G6/[2]BS!G22 -> 1.405462 | H14: =[2]BS!H6/[2]BS!H22 -> 1.1173763 | I14: =[2]BS!I6/[2]BS!I22 -> 1.1337105 | ... K14: =[2]BS!K6/[2]BS!K22 -> 0.48695963
A15: Defensive Interval | B15: =[2]BS!B10/(SUM([2]IS!B7:B11)/365) -> 427.93103 | C15: =[2]BS!C10/(SUM([2]IS!C7:C11)/365) -> 448.62447 | D15: =[2]BS!D10/(SUM([2]IS!D7:D11)/365) -> 416.42443 | E15: =[2]BS!E10/(SUM([2]IS!E7:E11)/365) -> 392.98968 | F15: =[2]BS!F10/(SUM([2]IS!F7:F11)/365) -> 353.11809 | G15: =[2]BS!G10/(SUM([2]IS!G7:G11)/365) -> 308.78282 | H15: =[2]BS!H10/(SUM([2]IS!H7:H11)/365) -> 290.70457 | I15: =[2]BS!I10/(SUM([2]IS!I7:I11)/365) -> 305.4096 | ... K15: =[2]BS!K10/(SUM([2]IS!K7:K11)/365) -> 231.74723
A17: Solvency Ratios | B17: FY 2014 | C17: FY 2015 | D17: FY 2016 | E17: FY 2017 | F17: FY 2018 | G17: FY 2019 | H17: FY 2020 | I17: FY 2021 | J17: FY 2022 | K17: FY 2023
A18: A/E | B18: =[2]BS!B18/[2]BS!B33 -> 1.2792724 | C18: =[2]BS!C18/[2]BS!C33 -> 1.3065476 | D18: =[2]BS!D18/[2]BS!D33 -> 1.2162801 | E18: =[2]BS!E18/[2]BS!E33 -> 1.2053579 | F18: =[2]BS!F18/[2]BS!F33 -> 1.2221829 | G18: =[2]BS!G18/[2]BS!G33 -> 1.2932037 | H18: =[2]BS!H18/[2]BS!H33 -> 1.3942045 | I18: =[2]BS!I18/[2]BS!I33 -> 1.400211 | ... K18: =[2]BS!K18/[2]BS!K33 -> 1.6438551
A19: D/E | B19: =[2]BS!B23/[2]BS!B33 -> 0 | C19: =[2]BS!C23/[2]BS!C33 -> 0 | D19: =[2]BS!D23/[2]BS!D33 -> 0 | E19: =[2]BS!E23/[2]BS!E33 -> 0 | F19: =[2]BS!F23/[2]BS!F33 -> 0 | G19: =[2]BS!G23/[2]BS!G33 -> 0 | H19: =[2]BS!H23/[2]BS!H33 -> 0.060962274 | I19: =[2]BS!I23/[2]BS!I33 -> 0.059740564 | ... K19: =[2]BS!K23/[2]BS!K33 -> 0.093106405
A20: D/A | B20: =[2]BS!B23/[2]BS!B18 -> 0 | C20: =[2]BS!C23/[2]BS!C18 -> 0 | D20: =[2]BS!D23/[2]BS!D18 -> 0 | E20: =[2]BS!E23/[2]BS!E18 -> 0 | F20: =[2]BS!F23/[2]BS!F18 -> 0 | G20: =[2]BS!G23/[2]BS!G18 -> 0 | H20: =[2]BS!H23/[2]BS!H18 -> 0.04372549 | I20: =[2]BS!I23/[2]BS!I18 -> 0.042665402 | ... K20: =[2]BS!K23/[2]BS!K18 -> 0.056639057
A21: Interest Coverage Ratio | B21: =IFERROR([2]IS!B14/[2]IS!B15,"NA") -> 1637.4444 | C21: =IFERROR([2]IS!C14/[2]IS!C15,"NA") -> 1441.3333 | D21: =IFERROR([2]IS!D14/[2]IS!D15,"NA") -> NA | E21: =IFERROR([2]IS!E14/[2]IS!E15,"NA") -> NA | F21: =IFERROR([2]IS!F14/[2]IS!F15,"NA") -> NA | G21: =IFERROR([2]IS!G14/[2]IS!G15,"NA") -> NA | H21: =IFERROR([2]IS!H14/[2]IS!H15,"NA") -> 130.45294 | I21: =IFERROR([2]IS!I14/[2]IS!I15,"NA") -> 137.55385 | ... K21: =IFERROR([2]IS!K14/[2]IS!K15,"NA") -> 118.33099
A23: Activity Ratios | B23: FY 2014 | C23: FY 2015 | D23: FY 2016 | E23: FY 2017 | F23: FY 2018 | G23: FY 2019 | H23: FY 2020 | I23: FY 2021 | J23: FY 2022 | K23: FY 2023
A24: Asset Turnover Ratio | C24: =[2]IS!C6/AVERAGE([2]BS!B18:C18) -> 0.92083891 | D24: =[2]IS!D6/AVERAGE([2]BS!C18:D18) -> 0.92739785 | E24: =[2]IS!E6/AVERAGE([2]BS!D18:E18) -> 0.90408604 | F24: =[2]IS!F6/AVERAGE([2]BS!E18:F18) -> 0.90873062 | G24: =[2]IS!G6/AVERAGE([2]BS!F18:G18) -> 1.0471132 | H24: =[2]IS!H6/AVERAGE([2]BS!G18:H18) -> 1.0643786 | I24: =[2]IS!I6/AVERAGE([2]BS!H18:I18) -> 1.0302793 | J24: =[2]IS!J6/AVERAGE([2]BS!I18:J18) -> 1.1053871 | K24: =[2]IS!K6/AVERAGE([2]BS!J18:K18) -> 1.2387279
A25: Receivables Turnover Ratio | C25: =[2]IS!C6/AVERAGE([2]BS!B7:C7) -> 6.2831045 | D25: =[2]IS!D6/AVERAGE([2]BS!C7:D7) -> 6.2311457 | E25: =[2]IS!E6/AVERAGE([2]BS!D7:E7) -> 6.0488754 | F25: =[2]IS!F6/AVERAGE([2]BS!E7:F7) -> 5.7990104 | G25: =[2]IS!G6/AVERAGE([2]BS!F7:G7) -> 6.1179878 | H25: =[2]IS!H6/AVERAGE([2]BS!G7:H7) -> 5.618899 | I25: =[2]IS!I6/AVERAGE([2]BS!H7:I7) -> 5.4351658 | J25: =[2]IS!J6/AVERAGE([2]BS!I7:J7) -> 5.9028386 | K25: =[2]IS!K6/AVERAGE([2]BS!J7:K7) -> 6.2120444
A26: Inventory Turnover Ratio | C26: =IFERROR(([2]IS!C7+[2]IS!C11)/AVERAGE([2]BS!B8:C8),"NA") -> NA | D26: =IFERROR(([2]IS!D7+[2]IS!D11)/AVERAGE([2]BS!C8:D8),"NA") -> NA | E26: =IFERROR(([2]IS!E7+[2]IS!E11)/AVERAGE([2]BS!D8:E8),"NA") -> NA | F26: =IFERROR(([2]IS!F7+[2]IS!F11)/AVERAGE([2]BS!E8:F8),"NA") -> NA | G26: =IFERROR(([2]IS!G7+[2]IS!G11)/AVERAGE([2]BS!F8:G8),"NA") -> NA | H26: =IFERROR(([2]IS!H7+[2]IS!H11)/AVERAGE([2]BS!G8:H8),"NA") -> NA | I26: =IFERROR(([2]IS!I7+[2]IS!I11)/AVERAGE([2]BS!H8:I8),"NA") -> NA | J26: =IFERROR(([2]IS!J7+[2]IS!J11)/AVERAGE([2]BS!I8:J8),"NA") -> NA | K26: =IFERROR(([2]IS!K7+[2]IS!K11)/AVERAGE([2]BS!J8:K8),"NA") -> NA
A27: Payables Turnover Ratio | C27: =([2]IS!C7+[2]IS!C11)/AVERAGE([2]BS!B19:C19) -> 32.083067 | D27: =([2]IS!D7+[2]IS!D11)/AVERAGE([2]BS!C19:D19) -> 20.721582 | E27: =([2]IS!E7+[2]IS!E11)/AVERAGE([2]BS!D19:E19) -> 16.777778 | F27: =([2]IS!F7+[2]IS!F11)/AVERAGE([2]BS!E19:F19) -> 12.667722 | G27: =([2]IS!G7+[2]IS!G11)/AVERAGE([2]BS!F19:G19) -> 7.1748428 | H27: =([2]IS!H7+[2]IS!H11)/AVERAGE([2]BS!G19:H19) -> 4.402343 | I27: =([2]IS!I7+[2]IS!I11)/AVERAGE([2]BS!H19:I19) -> 4.4564086 | J27: =([2]IS!J7+[2]IS!J11)/AVERAGE([2]BS!I19:J19) -> 5.7290595 | K27: =([2]IS!K7+[2]IS!K11)/AVERAGE([2]BS!J19:K19) -> 6.1043497
A28: Receivable Days (DSO) | C28: =365/C25 -> 58.092301 | D28: =365/D25 -> 58.576707 | E28: =365/E25 -> 60.341796 | F28: =365/F25 -> 62.941774 | G28: =365/G25 -> 59.660139 | H28: =365/H25 -> 64.959346 | I28: =365/I25 -> 67.155265 | J28: =365/J25 -> 61.834657 | K28: =365/K25 -> 58.756824
A29: Inventory Days (DIH) | C29: 0 | D29: 0 | E29: 0 | F29: 0 | G29: 0 | H29: 0 | I29: 0 | J29: 0 | K29: 0
A30: Payable Days | C30: =365/C27 -> 11.376718 | D30: =365/D27 -> 17.614486 | E30: =365/E27 -> 21.754967 | F30: =365/F27 -> 28.81339 | G30: =365/G27 -> 50.872195 | H30: =365/H27 -> 82.910395 | I30: =365/I27 -> 81.904519 | J30: =365/J27 -> 63.710283 | K30: =365/K27 -> 59.793429
A32: Operating Cycle | C32: =C28+C29 -> 58.092301 | D32: =D28+D29 -> 58.576707 | E32: =E28+E29 -> 60.341796 | F32: =F28+F29 -> 62.941774 | G32: =G28+G29 -> 59.660139 | H32: =H28+H29 -> 64.959346 | I32: =I28+I29 -> 67.155265 | J32: =J28+J29 -> 61.834657 | K32: =K28+K29 -> 58.756824
A33: Net Operating Cycle (CCC) | C33: =C28+C29-C30 -> 46.715583 | D33: =D28+D29-D30 -> 40.962222 | E33: =E28+E29-E30 -> 38.586829 | F33: =F28+F29-F30 -> 34.128384 | G33: =G28+G29-G30 -> 8.7879439 | H33: =H28+H29-H30 -> -17.951049 | I33: =I28+I29-I30 -> -14.749254 | J33: =J28+J29-J30 -> -1.8756261 | K33: =K28+K29-K30 -> -1.0366044

Sheet Ratio Analysis - HCL
A2: Profitability Ratios | B2: FY 2014 | C2: FY 2015 | D2: FY 2016 | E2: FY 2017 | F2: FY 2018 | G2: FY 2019 | H2: FY 2020 | I2: FY 2021 | J2: FY 2022 | K2: FY 2023
A3: EBITDA Margin | B3: =[3]IS!B12/[3]IS!B6 -> 0.26546035 | C3: =[3]IS!C12/[3]IS!C6 -> 0.25401341 | D3: =[3]IS!D12/[3]IS!D6 -> 0.23508857 | E3: =[3]IS!E12/[3]IS!E6 -> 0.23557346 | F3: =[3]IS!F12/[3]IS!F6 -> 0.24085407 | G3: =[3]IS!G12/[3]IS!G6 -> 0.2422845 | H3: =[3]IS!H12/[3]IS!H6 -> 0.25124535 | I3: =[3]IS!I12/[3]IS!I6 -> 0.27488009 | ... K3: =[3]IS!K12/[3]IS!K6 -> 0.23329508
A4: EBIT Margin | B4: =[3]IS!B14/[3]IS!B6 -> 0.24471574 | C4: =[3]IS!C14/[3]IS!C6 -> 0.24334367 | D4: =[3]IS!D14/[3]IS!D6 -> 0.22228318 | E4: =[3]IS!E14/[3]IS!E6 -> 0.21855149 | F4: =[3]IS!F14/[3]IS!F6 -> 0.21415471 | G4: =[3]IS!G14/[3]IS!G6 -> 0.20850578 | H4: =[3]IS!H14/[3]IS!H6 -> 0.20325545 | I4: =[3]IS!I14/[3]IS!I6 -> 0.21445234 | ... K4: =[3]IS!K14/[3]IS!K6 -> 0.19297956
A5: EBT Margin | B5: =[3]IS!B16/[3]IS!B6 -> 0.24122713 | C5: =[3]IS!C16/[3]IS!C6 -> 0.24093277 | D5: =[3]IS!D16/[3]IS!D6 -> 0.2199743 | E5: =[3]IS!E16/[3]IS!E6 -> 0.21672183 | F5: =[3]IS!F16/[3]IS!F6 -> 0.21282264 | G5: =[3]IS!G16/[3]IS!G6 -> 0.20567052 | H5: =[3]IS!H16/[3]IS!H6 -> 0.19616923 | I5: =[3]IS!I16/[3]IS!I6 -> 0.20775562 | ... K5: =[3]IS!K16/[3]IS!K6 -> 0.18954617
A6: PAT Margin | B6: =[3]IS!B18/[3]IS!B6 -> 0.19833333 | C6: =[3]IS!C18/[3]IS!C6 -> 0.19336518 | D6: =[3]IS!D18/[3]IS!D6 -> 0.17503858 | E6: =[3]IS!E18/[3]IS!E6 -> 0.17692165 | F6: =[3]IS!F18/[3]IS!F6 -> 0.16836232 | G6: =[3]IS!G18/[3]IS!G6 -> 0.16490142 | H6: =[3]IS!H18/[3]IS!H6 -> 0.1551533 | I6: =[3]IS!I18/[3]IS!I6 -> 0.14605667 | ... K6: =[3]IS!K18/[3]IS!K6 -> 0.14444531
A7: ROA | C7: =[3]IS!C18/AVERAGE([3]BS!B18:C18) -> 0.22436617 | D7: =[3]IS!D18/AVERAGE([3]BS!C18:D18) -> 0.15022886 | E7: =[3]IS!E18/AVERAGE([3]BS!D18:E18) -> 0.20224999 | F7: =[3]IS!F18/AVERAGE([3]BS!E18:F18) -> 0.18604602 | G7: =[3]IS!G18/AVERAGE([3]BS!F18:G18) -> 0.19033647 | H7: =[3]IS!H18/AVERAGE([3]BS!G18:H18) -> 0.15665023 | I7: =[3]IS!I18/AVERAGE([3]BS!H18:I18) -> 0.13199815 | J7: =[3]IS!J18/AVERAGE([3]BS!I18:J18) -> 0.1543025 | K7: =[3]IS!K18/AVERAGE([3]BS!J18:K18) -> 0.16304461
A8: ROE | C8: =[3]IS!C18/AVERAGE([3]BS!B33:C33) -> 0.33324786 | D8: =[3]IS!D18/AVERAGE([3]BS!C33:D33) -> 0.21586019 | E8: =[3]IS!E18/AVERAGE([3]BS!D33:E33) -> 0.28344907 | F8: =[3]IS!F18/AVERAGE([3]BS!E33:F33) -> 0.25093514 | G8: =[3]IS!G18/AVERAGE([3]BS!F33:G33) -> 0.25997046 | H8: =[3]IS!H18/AVERAGE([3]BS!G33:H33) -> 0.23806653 | I8: =[3]IS!I18/AVERAGE([3]BS!H33:I33) -> 0.19990494 | J8: =[3]IS!J18/AVERAGE([3]BS!I33:J33) -> 0.22113557 | K8: =[3]IS!K18/AVERAGE([3]BS!J33:K33) -> 0.2331324
A9: ROCE | C9: =[3]IS!B14/(AVERAGE([3]BS!B33:C33)+AVERAGE([3]BS!B23:C23)) -> 0.36275651 | D9: =[3]IS!C14/(AVERAGE([3]BS!C33:D33)+AVERAGE([3]BS!C23:D23)) -> 0.34871142 | E9: =[3]IS!D14/(AVERAGE([3]BS!D33:E33)+AVERAGE([3]BS!D23:E23)) -> 0.23008213 | F9: =[3]IS!E14/(AVERAGE([3]BS!E33:F33)+AVERAGE([3]BS!E23:F23)) -> 0.30275242 | G9: =[3]IS!F14/(AVERAGE([3]BS!F33:G33)+AVERAGE([3]BS!F23:G23)) -> 0.27332758 | H9: =[3]IS!G14/(AVERAGE([3]BS!G33:H33)+AVERAGE([3]BS!G23:H23)) -> 0.25365235 | I9: =[3]IS!H14/(AVERAGE([3]BS!H33:I33)+AVERAGE([3]BS!H23:I23)) -> 0.23695209 | J9: =[3]IS!I14/(AVERAGE([3]BS!I33:J33)+AVERAGE([3]BS!I23:J23)) -> 0.24533549 | K9: =[3]IS!J14/(AVERAGE([3]BS!J33:K33)+AVERAGE([3]BS!J23:K23)) -> 0.25255738
A11: Liquidity Ratios | B11: FY 2014 | C11: FY 2015 | D11: FY 2016 | E11: FY 2017 | F11: FY 2018 | G11: FY 2019 | H11: FY 2020 | I11: FY 2021 | J11: FY 2022 | K11: FY 2023
A12: Current Ratio | B12: =[3]BS!B10/[3]BS!B22 -> 2.0915484 | C12: =[3]BS!C10/[3]BS!C22 -> 2.3174142 | D12: =[3]BS!D10/[3]BS!D22 -> 2.5417741 | E12: =[3]BS!E10/[3]BS!E22 -> 2.3346273 | F12: =[3]BS!F10/[3]BS!F22 -> 2.4298011 | G12: =[3]BS!G10/[3]BS!G22 -> 2.4166192 | H12: =[3]BS!H10/[3]BS!H22 -> 1.6190476 | I12: =[3]BS!I10/[3]BS!I22 -> 2.4766151 | ... K12: =[3]BS!K10/[3]BS!K22 -> 2.4999767
A13: Quick Ratio | B13: =([3]BS!B6+[3]BS!B7)/[3]BS!B21 -> 1.8924116 | C13: =([3]BS!C6+[3]BS!C7)/[3]BS!C21 -> 2.0019096 | D13: =([3]BS!D6+[3]BS!D7)/[3]BS!D21 -> 2.0574264 | E13: =([3]BS!E6+[3]BS!E7)/[3]BS!E21 -> 2.1800283 | F13: =([3]BS!F6+[3]BS!F7)/[3]BS!F21 -> 1.9755736 | G13: =([3]BS!G6+[3]BS!G7)/[3]BS!G21 -> 2.1071049 | H13: =([3]BS!H6+[3]BS!H7)/[3]BS!H21 -> 1.190348 | I13: =([3]BS!I6+[3]BS!I7)/[3]BS!I21 -> 2.9388948 | ... K13: =([3]BS!K6+[3]BS!K7)/[3]BS!K21 -> 3.1337593
A14: Cash Ratio | B14: =[3]BS!B6/[3]BS!B21 -> 1.1800397 | C14: =[3]BS!C6/[3]BS!C21 -> 1.2358604 | D14: =[3]BS!D6/[3]BS!D21 -> 1.1544314 | E14: =[3]BS!E6/[3]BS!E21 -> 1.2013676 | F14: =[3]BS!F6/[3]BS!F21 -> 0.78645448 | G14: =[3]BS!G6/[3]BS!G21 -> 0.97554374 | H14: =[3]BS!H6/[3]BS!H21 -> 0.54577384 | I14: =[3]BS!I6/[3]BS!I21 -> 1.3869111 | ... K14: =[3]BS!K6/[3]BS!K21 -> 1.3814922
A15: Defensive Interval | B15: =[3]BS!B10/(SUM([3]IS!B7:B11)/365) -> 292.65002 | C15: =[3]BS!C10/(SUM([3]IS!C7:C11)/365) -> 297.99813 | D15: =[3]BS!D10/(SUM([3]IS!D7:D11)/365) -> 372.44405 | E15: =[3]BS!E10/(SUM([3]IS!E7:E11)/365) -> 259.76213 | F15: =[3]BS!F10/(SUM([3]IS!F7:F11)/365) -> 227.9498 | G15: =[3]BS!G10/(SUM([3]IS!G7:G11)/365) -> 233.2967 | H15: =[3]BS!H10/(SUM([3]IS!H7:H11)/365) -> 262.80547 | I15: =[3]BS!I10/(SUM([3]IS!I7:I11)/365) -> 283.99297 | ... K15: =[3]BS!K10/(SUM([3]IS!K7:K11)/365) -> 248.07943
A17: Solvency Ratios | B17: FY 2014 | C17: FY 2015 | D17: FY 2016 | E17: FY 2017 | F17: FY 2018 | G17: FY 2019 | H17: FY 2020 | I17: FY 2021 | J17: FY 2022 | K17: FY 2023
A18: A/E | B18: =[3]BS!B18/[3]BS!B33 -> 1.5290175 | C18: =[3]BS!C18/[3]BS!C33 -> 1.4500089 | D18: =[3]BS!D18/[3]BS!D33 -> 1.4253102 | E18: =[3]BS!E18/[3]BS!E33 -> 1.3816195 | F18: =[3]BS!F18/[3]BS!F33 -> 1.3188864 | G18: =[3]BS!G18/[3]BS!G33 -> 1.4070511 | H18: =[3]BS!H18/[3]BS!H33 -> 1.6106066 | I18: =[3]BS!I18/[3]BS!I33 -> 1.4321594 | ... K18: =[3]BS!K18/[3]BS!K33 -> 1.4258846
A19: D/E | B19: =[3]BS!B23/[3]BS!B33 -> 0.010232997 | C19: =[3]BS!C23/[3]BS!C33 -> 0.0069072002 | D19: =[3]BS!D23/[3]BS!D33 -> 0.026716007 | E19: =[3]BS!E23/[3]BS!E33 -> 0.011563311 | F19: =[3]BS!F23/[3]BS!F33 -> 0.0092892871 | G19: =[3]BS!G23/[3]BS!G33 -> 0.071788565 | H19: =[3]BS!H23/[3]BS!H33 -> 0.097761615 | I19: =[3]BS!I23/[3]BS!I33 -> 0.095386305 | ... K19: =[3]BS!K23/[3]BS!K33 -> 0.057723478
A20: D/A | B20: =[3]BS!B23/[3]BS!B18 -> 0.0066925308 | C20: =[3]BS!C23/[3]BS!C18 -> 0.0047635572 | D20: =[3]BS!D23/[3]BS!D18 -> 0.018743995 | E20: =[3]BS!E23/[3]BS!E18 -> 0.0083693894 | F20: =[3]BS!F23/[3]BS!F18 -> 0.0070432808 | G20: =[3]BS!G23/[3]BS!G18 -> 0.051020583 | H20: =[3]BS!H23/[3]BS!H18 -> 0.060698632 | I20: =[3]BS!I23/[3]BS!I18 -> 0.066603135 | ... K20: =[3]BS!K23/[3]BS!K18 -> 0.040482574
A21: Interest Coverage Ratio | B21: =[3]IS!B14/[3]IS!B15 -> 70.146987 | C21: =[3]IS!C14/[3]IS!C15 -> 100.93489 | D21: =[3]IS!D14/[3]IS!D15 -> 96.273072 | E21: =[3]IS!E14/[3]IS!E15 -> 119.44944 | F21: =[3]IS!F14/[3]IS!F15 -> 160.76812 | G21: =[3]IS!G14/[3]IS!G15 -> 73.54023 | H21: =[3]IS!H14/[3]IS!H15 -> 28.683168 | I21: =[3]IS!I14/[3]IS!I15 -> 32.023483 | ... K21: =[3]IS!K14/[3]IS!K15 -> 56.206799
A23: Activity Ratios | B23: FY 2014 | C23: FY 2015 | D23: FY 2016 | E23: FY 2017 | F23: FY 2018 | G23: FY 2019 | H23: FY 2020 | I23: FY 2021 | J23: FY 2022 | K23: FY 2023
A24: Asset Turnover Ratio | C24: =[3]IS!C6/AVERAGE([3]BS!B18:C18) -> 1.1603235 | D24: =[3]IS!D6/AVERAGE([3]BS!C18:D18) -> 0.85826142 | E24: =[3]IS!E6/AVERAGE([3]BS!D18:E18) -> 1.1431613 | F24: =[3]IS!F6/AVERAGE([3]BS!E18:F18) -> 1.1050335 | G24: =[3]IS!G6/AVERAGE([3]BS!F18:G18) -> 1.154244 | H24: =[3]IS!H6/AVERAGE([3]BS!G18:H18) -> 1.0096481 | I24: =[3]IS!I6/AVERAGE([3]BS!H18:I18) -> 0.90374617 | J24: =[3]IS!J6/AVERAGE([3]BS!I18:J18) -> 0.99124411 | K24: =[3]IS!K6/AVERAGE([3]BS!J18:K18) -> 1.1287636
A25: Receivables Turnover Ratio | C25: =[3]IS!C6/AVERAGE([3]BS!B7:C7) -> 6.192462 | D25: =[3]IS!D6/AVERAGE([3]BS!C7:D7) -> 4.48909 | E25: =[3]IS!E6/AVERAGE([3]BS!D7:E7) -> 6.0719729 | F25: =[3]IS!F6/AVERAGE([3]BS!E7:F7) -> 5.7746934 | G25: =[3]IS!G6/AVERAGE([3]BS!F7:G7) -> 5.7502928 | H25: =[3]IS!H6/AVERAGE([3]BS!G7:H7) -> 5.5165073 | I25: =[3]IS!I6/AVERAGE([3]BS!H7:I7) -> 4.8209502 | J25: =[3]IS!J6/AVERAGE([3]BS!I7:J7) -> 4.5406849 | K25: =[3]IS!K6/AVERAGE([3]BS!J7:K7) -> 4.4530394
A26: Inventory Turnover Ratio | C26: =([3]IS!C7+[3]IS!C11)/AVERAGE([3]BS!B8:C8) -> 52.760959 | D26: =([3]IS!D7+[3]IS!D11)/AVERAGE([3]BS!C8:D8) -> 32.519557 | E26: =([3]IS!E7+[3]IS!E11)/AVERAGE([3]BS!D8:E8) -> 40.789668 | F26: =([3]IS!F7+[3]IS!F11)/AVERAGE([3]BS!E8:F8) -> 51.209821 | G26: =([3]IS!G7+[3]IS!G11)/AVERAGE([3]BS!F8:G8) -> 101.61977 | H26: =([3]IS!H7+[3]IS!H11)/AVERAGE([3]BS!G8:H8) -> 165.65934 | I26: =([3]IS!I7+[3]IS!I11)/AVERAGE([3]BS!H8:I8) -> 156.99459 | J26: =([3]IS!J7+[3]IS!J11)/AVERAGE([3]BS!I8:J8) -> 132.03922 | K26: =([3]IS!K7+[3]IS!K11)/AVERAGE([3]BS!J8:K8) -> 105.56812
A27: Payables Turnover Ratio | C27: =([3]IS!C7+[3]IS!C11)/AVERAGE([3]BS!B19:C19) -> 5.5231798 | D27: =([3]IS!D7+[3]IS!D11)/AVERAGE([3]BS!C19:D19) -> 5.1077769 | E27: =([3]IS!E7+[3]IS!E11)/AVERAGE([3]BS!D19:E19) -> 5.3369032 | F27: =([3]IS!F7+[3]IS!F11)/AVERAGE([3]BS!E19:F19) -> 4.7264112 | G27: =([3]IS!G7+[3]IS!G11)/AVERAGE([3]BS!F19:G19) -> 6.7575221 | H27: =([3]IS!H7+[3]IS!H11)/AVERAGE([3]BS!G19:H19) -> 8.016485 | I27: =([3]IS!I7+[3]IS!I11)/AVERAGE([3]BS!H19:I19) -> 3.6773867 | J27: =([3]IS!J7+[3]IS!J11)/AVERAGE([3]BS!I19:J19) -> 2.5915948 | K27: =([3]IS!K7+[3]IS!K11)/AVERAGE([3]BS!J19:K19) -> 2.9809814
A28: Receivable Days (DSO) | C28: =365/C25 -> 58.942631 | D28: =365/D25 -> 81.308239 | E28: =365/E25 -> 60.112258 | F28: =365/F25 -> 63.206819 | G28: =365/G25 -> 63.475029 | H28: =365/H25 -> 66.165053 | I28: =365/I25 -> 75.711215 | J28: =365/J25 -> 80.384349 | K28: =365/K25 -> 81.966488
A29: Inventory Days (DIH) | C29: =365/C26 -> 6.9179941 | D29: =365/D26 -> 11.224015 | E29: =365/E26 -> 8.9483444 | F29: =365/F26 -> 7.127539 | G29: =365/G26 -> 3.5918207 | H29: =365/H26 -> 2.2033167 | I29: =365/I26 -> 2.3249208 | J29: =365/J26 -> 2.7643303 | K29: =365/K26 -> 3.4574831
A30: Payable Days | C30: =365/C27 -> 66.08512 | D30: =365/D27 -> 71.45966 | E30: =365/E27 -> 68.391722 | F30: =365/F27 -> 77.225612 | G30: =365/G27 -> 54.013882 | H30: =365/H27 -> 45.531177 | I30: =365/I27 -> 99.255268 | J30: =365/J27 -> 140.83992 | K30: =365/K27 -> 122.4429
A32: Operating Cycle | C32: =C28+C29 -> 65.860625 | D32: =D28+D29 -> 92.532254 | E32: =E28+E29 -> 69.060602 | F32: =F28+F29 -> 70.334358 | G32: =G28+G29 -> 67.066849 | H32: =H28+H29 -> 68.36837 | I32: =I28+I29 -> 78.036136 | J32: =J28+J29 -> 83.14868 | K32: =K28+K29 -> 85.423971
A33: Net Operating Cycle (CCC) | C33: =C28+C29-C30 -> -0.22449533 | D33: =D28+D29-D30 -> 21.072594 | E33: =E28+E29-E30 -> 0.66888019 | F33: =F28+F29-F30 -> -6.8912547 | G33: =G28+G29-G30 -> 13.052968 | H33: =H28+H29-H30 -> 22.837192 | I33: =I28+I29-I30 -> -21.219132 | J33: =J28+J29-J30 -> -57.691237 | K33: =K28+K29-K30 -> -37.018926
