Workbook

Sheet IS
A2: Infosys Ltd (INFY)
A5: Income Statement (All numbers in INR crores except EPS and DPS) | B5: FY 2014 | C5: FY 2015 | D5: FY 2016 | E5: FY 2017 | F5: FY 2018 | G5: FY 2019 | H5: FY 2020 | I5: FY 2021 | J5: FY 2022 | K5: FY 2023
A6: 'Total Revenue' | B6: 52797 | C6: 56749 | D6: 65561 | E6: 71534 | F6: 73833 | G6: 85557 | H6: 93594 | I6: 102673 | J6: 123936 | K6: 149468
A7: y-o-y growth in revenue | C7: =C6/B6-1 -> 0.074852738 | D7: =D6/C6-1 -> 0.15528027 | E7: =E6/D6-1 -> 0.091105993 | F7: =F6/E6-1 -> 0.032138563 | G7: =G6/F6-1 -> 0.15879078 | H7: =H6/G6-1 -> 0.093937375 | I7: =I6/H6-1 -> 0.097004081 | J7: =J6/I6-1 -> 0.20709437 | K7: =K6/J6-1 -> 0.20600955
A8: '- Raw Materials' | B8: 0 | C8: 0 | D8: 0 | E8: 0 | F8: 0 | G8: 0 | H8: 0 | I8: 0 | J8: 0 | K8: 0
A9: '- Power & Fuel Cost' | B9: 219 | C9: 219 | D9: 217 | E9: 228 | F9: 207 | G9: 221 | H9: 229 | I9: 143 | J9: 132 | K9: 176
A10: '- Employee Cost' | B10: 28831 | C10: 29802 | D10: 34406 | E10: 37659 | F10: 38893 | G10: 45315 | H10: 50887 | I10: 55541 | J10: 63986 | K10: 78359
A11: '- Selling & Administrative Expenses' | B11: 3600 | C11: 3394 | D11: 4450 | E11: 4594 | F11: 4594 | G11: 5561 | H11: 5383 | I11: 3200 | J11: 4316 | K11: 5315
A12: '- Operating & Other expenses' | B12: 4093 | C12: 5021 | D12: 6289 | E12: 7399 | F12: 8006 | G12: 11408 | H12: 12025 | I12: 13699 | J12: 21716 | K12: 27787
A13: '= EBITDA' | B13: 16054 | C13: 18313 | D13: 20199 | E13: 21654 | F13: 22133 | G13: 23052 | H13: 25070 | I13: 30090 | J13: 33786 | K13: 37831
A14: '- Depreciation/Amortization' | B14: 1317 | C14: 1017 | D14: 1459 | E14: 1703 | F14: 1863 | G14: 2011 | H14: 2893 | I14: 3267 | J14: 3476 | K14: 4225
A15: '= PBIT' | B15: 14737 | C15: 17296 | D15: 18740 | E15: 19951 | F15: 20270 | G15: 21041 | H15: 22177 | I15: 26823 | J15: 30310 | K15: 33606
A16: '- Interest & Other Items' | B16: 9 | C16: 12 | D16: 0 | E16: 0 | F16: 0 | G16: 0 | H16: 170 | I16: 195 | J16: 200 | K16: 284
A17: '= PBT' | B17: 14728 | C17: 17284 | D17: 18740 | E17: 19951 | F17: 20270 | G17: 21041 | H17: 22007 | I17: 26628 | J17: 30110 | K17: 33322
A18: '- Taxes & Other Items' | B18: 4072 | C18: 4912 | D18: 5251 | E18: 5598 | F18: 4241 | G18: 5637 | H18: 5413 | I18: 7277 | J18: 8000 | K18: 9227
A19: '= Net Income' | B19: 10656 | C19: 12372 | D19: 13489 | E19: 14353 | F19: 16029 | G19: 15404 | H19: 16594 | I19: 19351 | J19: 22110 | K19: 24095
... A23: 'Payout ratio' | B23: 0.34 | C23: 0.55 | D23: 0.41 | E23: 0.41 | F23: 0.61 | G23: 0.61 | H23: 0.45 | I23: 0.59 | J23: 0.59 | K23: 0.59

Sheet BS
A2: Infosys Ltd (INFY)
A5: Balance Sheet (All numbers in INR crores) | B5: FY 2014 | C5: FY 2015 | D5: FY 2016 | E5: FY 2017 | F5: FY 2018 | G5: FY 2019 | H5: FY 2020 | I5: FY 2021 | J5: FY 2022 | K5: FY 2023
A6: 'Cash and Short Term Investments' | B6: 28974 | C6: 31239 | D6: 32772 | E6: 32595 | F6: 26225 | G6: 26195 | H6: 23304 | I6: 27056 | J6: 24145 | K6: 19082
A7: '+ Total Receivables' | B7: 8351 | C7: 9713 | D7: 11330 | E7: 12322 | F7: 13142 | G7: 14827 | H7: 18487 | I7: 19294 | J7: 22698 | K7: 25424
A8: '+ Total Inventory' | B8: 0 | C8: 0 | D8: 0 | E8: 0 | F8: 0 | G8: 0 | H8: 0 | I8: 0 | J8: 0 | K8: 0
A9: '+ Other Current Assets' | B9: 5753 | C9: 6290 | D9: 7651 | E9: 8788 | F9: 10650 | G9: 11856 | H9: 12785 | I9: 14383 | J9: 20342 | K9: 26375
A10: '= Total Current Assets (A1)' | B10: 43078 | C10: 47242 | D10: 51753 | E10: 53705 | F10: 50017 | G10: 52878 | H10: 54576 | I10: 60733 | J10: 67185 | K10: 70881
A11: 'Loans & Advances' | B11: - | C11: - | D11: - | E11: - | F11: - | G11: - | H11: - | I11: - | J11: - | K11: -
A12: '+ Net Property/Plant/Equipment' | B12: 7095 | C12: 8527 | D12: 10527 | E12: 11851 | F12: 11955 | G12: 13503 | H12: 19282 | I12: 20154 | J12: 19863 | K12: 22114
A13: '+ Goodwill & Intangibles' | B13: 2244 | C13: 3595 | D13: 3819 | E13: 3693 | F13: 2225 | G13: 3595 | H13: 5461 | I13: 6273 | J13: 6353 | K13: 7399
A14: '+ Long Term Investments' | B14: 1307 | C14: 1398 | D14: 1817 | E14: 6453 | F14: 5756 | G14: 4634 | H14: 4137 | I14: 11863 | J14: 13651 | K14: 12569
A15: '+ Deferred Tax Assets (Net)' | B15: 629 | C15: 536 | D15: 284 | E15: 333 | F15: 741 | G15: 700 | H15: 776 | I15: 223 | J15: 56 | K15: 25
A16: '+ Other Assets' | B16: 2613 | C16: 4991 | D16: 6898 | E16: 7113 | F16: 8655 | G16: 8756 | H16: 7568 | I16: 8265 | J16: 9621 | K16: 11608
A17: '= Non Current Assets (A2)' | B17: 13888 | C17: 19047 | D17: 23345 | E17: 29443 | F17: 29332 | G17: 31188 | H17: 37224 | I17: 46778 | J17: 49544 | K17: 53715
A18: 'Total Assets (A1 + A2)' | B18: 56966 | C18: 66289 | D18: 75098 | E18: 83148 | F18: 79349 | G18: 84066 | H18: 91800 | I18: 107511 | J18: 116729 | K18: 124596
A19: 'Accounts Payable' | B19: 173 | C19: 140 | D19: 467 | E19: 415 | F19: 849 | G19: 2331 | H19: 3132 | I19: 3016 | J19: 4565 | K19: 4539
A20: '+ Total Deposits' | B20: - | C20: - | D20: - | E20: - | F20: - | G20: - | H20: - | I20: - | J20: - | K20: -
A21: '+ Other Current Liabilities' | B21: 11858 | C21: 15363 | D21: 12772 | E21: 13598 | F21: 13256 | G21: 16307 | H21: 17724 | I21: 20849 | J21: 29038 | K21: 34647
A22: '= Current Liabilities' | B22: 12031 | C22: 15503 | D22: 13239 | E22: 14013 | F22: 14105 | G22: 18638 | H22: 20856 | I22: 23865 | J22: 33603 | K22: 39186
A23: 'Total Long Term Debt' | B23: 0 | C23: 0 | D23: 0 | E23: 0 | F23: 0 | G23: 0 | H23: 4014 | I23: 4587 | J23: 4602 | K23: 7057
A24: '+ Deferred Tax Liabilities (Net)' | B24: - | C24: - | D24: - | E24: - | F24: - | G24: - | H24: - | I24: - | J24: - | K24: -
A25: '+ Other Liabilities' | B25: 405 | C25: 50 | D25: 115 | E25: 153 | F25: 320 | G25: 422 | H25: 1086 | I25: 2277 | J25: 2788 | K25: 2558
A26: '= Non Current Liabilities' | B26: 405 | C26: 50 | D26: 115 | E26: 153 | F26: 320 | G26: 422 | H26: 5100 | I26: 6864 | J26: 7390 | K26: 9615
A27: 'Total Liabilities' | B27: 12436 | C27: 15553 | D27: 13354 | E27: 14166 | F27: 14425 | G27: 19060 | H27: 25956 | I27: 30729 | J27: 40993 | K27: 48801
A28: 'Common Stock' | B28: 286 | C28: 572 | D28: 1144 | E28: 1144 | F28: 1088 | G28: 2170 | H28: 2122 | I28: 2124 | J28: 2098 | K28: 2069
A29: '+ Additional Paid-in Capital' | B29: 3070 | C29: 2784 | D29: 2213 | E29: 2216 | F29: 36 | G29: 149 | H29: 282 | I29: 600 | J29: 200 | K29: 166
A30: '+ Reserves & Surplus' | B30: 41174 | C30: 47380 | D30: 58387 | E30: 65622 | F30: 63799 | G30: 62629 | H30: 63046 | I30: 73627 | J30: 73052 | K30: 73172
A31: '+ Minority Interest' | B31: 0 | C31: 0 | D31: 0 | E31: 0 | F31: 1 | G31: 58 | H31: 394 | I31: 431 | J31: 386 | K31: 388
A32: '+ Other Equity' | B32: 0 | C32: 0 | D32: 0 | E32: 0 | F32: 0 | G32: 0 | H32: 0 | I32: 0 | J32: 0 | K32: 0
A33: 'Total Equity' | B33: 44530 | C33: 50736 | D33: 61744 | E33: 68982 | F33: 64924 | G33: 65006 | H33: 65844 | I33: 76782 | J33: 75736 | K33: 75795
A34: 'Total Liabilities & Shareholder's Equity' | B34: 56966 | C34: 66289 | D34: 75098 | E34: 83148 | F34: 79349 | G34: 84066 | H34: 91800 | I34: 107511 | J34: 116729 | K34: 124596
A35: 'Total Common Shares Outstanding' | B35: 457.12 | C35: 457.12 | D35: 457.12 | E35: 457.13 | F35: 434.66 | G35: 433.6 | H35: 424.08 | I35: 424.51 | J35: 419.3 | K35: 413.64
A37: Shares outstanding numbers in cr. Other numbers in â‚¹ cr
A38: Report generated on 12-Dec-23 at 12:50 PM

Sheet CFS
A2: Infosys Ltd (INFY)
A5: Cash Flow Statement (All numbers in INR crores) | B5: FY 2014 | C5: FY 2015 | D5: FY 2016 | E5: FY 2017 | F5: FY 2018 | G5: FY 2019 | H5: FY 2020 | I5: FY 2021 | J5: FY 2022 | K5: FY 2023
A6: 'Cash from Operating Activities' | B6: 9825 | C6: 8353 | D6: 10028 | E6: 11531 | F6: 13218 | G6: 14841 | H6: 17003 | I6: 23224 | J6: 23885 | K6: 22467
A7: '+ Cash from Investing Activities' | B7: -2563 | C7: 999 | D7: -885 | E7: -14664 | F7: 4533 | G7: -632 | H7: -331 | I7: -7373 | J7: -6485 | K7: -1071
A8: '+ Cash from Financing Activities' | B8: -3144 | C8: -4935 | D8: -6813 | E8: -6939 | F8: -20505 | G8: -14512 | H8: -17591 | I8: -9786 | J8: -24642 | K8: -26695
A9: '= Net Change in Cash' | B9: 4118 | C9: 4417 | D9: 2330 | E9: -10072 | F9: -2754 | G9: -303 | H9: -919 | I9: 6065 | J9: -7242 | K9: -5299
A10: 'Changes in Working Capital' | B10: -4347 | C10: -7593 | D10: -7811 | E10: -7809 | F10: -6745 | G10: -7285 | H10: -6917 | I10: -5621 | J10: -9036 | K10: -15138
A11: 'Capital Expenditures' | B11: 2748 | C11: 2247 | D11: 2723 | E11: 2760 | F11: 1998 | G11: 2445 | H11: 3307 | I11: 2107 | J11: 2161 | K11: 2579
A12: 'Free Cash Flow' | B12: 7077 | C12: 6106 | D12: 7305 | E12: 8771 | F12: 11220 | G12: 12396 | H12: 13696 | I12: 21117 | J12: 21724 | K12: 19888

Sheet Ratio Analysis-infy
A2: Profitability Ratios | B2: FY 2014 | C2: FY 2015 | D2: FY 2016 | E2: FY 2017 | F2: FY 2018 | G2: FY 2019 | H2: FY 2020 | I2: FY 2021 | J2: FY 2022 | K2: FY 2023
A3: EBITDA Margin | B3: =IS!B13/IS!B6 -> 0.30407031 | C3: =IS!C13/IS!C6 -> 0.32270172 | D3: =IS!D13/IS!D6 -> 0.30809475 | E3: =IS!E13/IS!E6 -> 0.3027092 | F3: =IS!F13/IS!F6 -> 0.29977111 | G3: =IS!G13/IS!G6 -> 0.26943441 | H3: =IS!H13/IS!H6 -> 0.26785905 | I3: =IS!I13/IS!I6 -> 0.29306634 | ... K3: =IS!K13/IS!K6 -> 0.25310434
A4: EBIT Margin | B4: =IS!B15/IS!B6 -> 0.27912571 | C4: =IS!C15/IS!C6 -> 0.3047807 | D4: =IS!D15/IS!D6 -> 0.28584067 | E4: =IS!E15/IS!E6 -> 0.27890234 | F4: =IS!F15/IS!F6 -> 0.27453849 | G4: =IS!G15/IS!G6 -> 0.24592961 | H4: =IS!H15/IS!H6 -> 0.23694895 | I4: =IS!I15/IS!I6 -> 0.26124687 | ... K4: =IS!K15/IS!K6 -> 0.22483742
A5: EBT Margin | B5: =IS!B17/IS!B6 -> 0.27895524 | C5: =IS!C17/IS!C6 -> 0.30456924 | D5: =IS!D17/IS!D6 -> 0.28584067 | E5: =IS!E17/IS!E6 -> 0.27890234 | F5: =IS!F17/IS!F6 -> 0.27453849 | G5: =IS!G17/IS!G6 -> 0.24592961 | H5: =IS!H17/IS!H6 -> 0.23513259 | I5: =IS!I17/IS!I6 -> 0.25934764 | ... K5: =IS!K17/IS!K6 -> 0.22293735
A6: PAT Margin | B6: =IS!B19/IS!B6 -> 0.20182965 | C6: =IS!C19/IS!C6 -> 0.21801265 | D6: =IS!D19/IS!D6 -> 0.20574732 | E6: =IS!E19/IS!E6 -> 0.20064585 | F6: =IS!F19/IS!F6 -> 0.21709805 | G6: =IS!G19/IS!G6 -> 0.18004371 | H6: =IS!H19/IS!H6 -> 0.17729769 | I6: =IS!I19/IS!I6 -> 0.18847214 | ... K6: =IS!K19/IS!K6 -> 0.16120507
A7: ROA | C7: =IS!C19/AVERAGE(BS!B18:C18) -> 0.20075453 | D7: =IS!D19/AVERAGE(BS!C18:D18) -> 0.19080962 | E7: =IS!E19/AVERAGE(BS!D18:E18) -> 0.18140111 | F7: =IS!F19/AVERAGE(BS!E18:F18) -> 0.19728364 | G7: =IS!G19/AVERAGE(BS!F18:G18) -> 0.18852615 | H7: =IS!H19/AVERAGE(BS!G18:H18) -> 0.18871186 | I7: =IS!I19/AVERAGE(BS!H18:I18) -> 0.19417895 | J7: =IS!J19/AVERAGE(BS!I18:J18) -> 0.19719943 | K7: =IS!K19/AVERAGE(BS!J18:K18) -> 0.19968922
A8: ROE | C8: =IS!C19/AVERAGE(BS!B33:C33) -> 0.2597359 | D8: =IS!D19/AVERAGE(BS!C33:D33) -> 0.23984708 | E8: =IS!E19/AVERAGE(BS!D33:E33) -> 0.21958906 | F8: =IS!F19/AVERAGE(BS!E33:F33) -> 0.23940675 | G8: =IS!G19/AVERAGE(BS!F33:G33) -> 0.23711229 | H8: =IS!H19/AVERAGE(BS!G33:H33) -> 0.25363393 | I8: =IS!I19/AVERAGE(BS!H33:I33) -> 0.27135305 | J8: =IS!J19/AVERAGE(BS!I33:J33) -> 0.28993299 | K8: =IS!K19/AVERAGE(BS!J33:K33) -> 0.31802074
A9: ROCE | C9: =IS!C15/(AVERAGE(BS!B33:C33)+AVERAGE(BS!B23:C23)) -> 0.36310961 | D9: =IS!D15/(AVERAGE(BS!C33:D33)+AVERAGE(BS!C23:D23)) -> 0.33321479 | E9: =IS!E15/(AVERAGE(BS!D33:E33)+AVERAGE(BS!D23:E23)) -> 0.30523385 | F9: =IS!F15/(AVERAGE(BS!E33:F33)+AVERAGE(BS!E23:F23)) -> 0.30274969 | G9: =IS!G15/(AVERAGE(BS!F33:G33)+AVERAGE(BS!F23:G23)) -> 0.32388209 | H9: =IS!H15/(AVERAGE(BS!G33:H33)+AVERAGE(BS!G23:H23)) -> 0.32887946 | I9: =IS!I15/(AVERAGE(BS!H33:I33)+AVERAGE(BS!H23:I23)) -> 0.35473824 | J9: =IS!J15/(AVERAGE(BS!I33:J33)+AVERAGE(BS!I23:J23)) -> 0.37487555 | K9: =IS!K15/(AVERAGE(BS!J33:K33)+AVERAGE(BS!J23:K23)) -> 0.41186347
A11: Liquidity Ratios | B11: FY 2014 | C11: FY 2015 | D11: FY 2016 | E11: FY 2017 | F11: FY 2018 | G11: FY 2019 | H11: FY 2020 | I11: FY 2021 | J11: FY 2022 | K11: FY 2023
A12: Current Ratio | B12: =BS!B10/BS!B22 -> 3.5805835 | C12: =BS!C10/BS!C22 -> 3.0472812 | D12: =BS!D10/BS!D22 -> 3.9091321 | E12: =BS!E10/BS!E22 -> 3.8325127 | F12: =BS!F10/BS!F22 -> 3.5460475 | G12: =BS!G10/BS!G22 -> 2.837107 | H12: =BS!H10/BS!H22 -> 2.6168009 | I12: =BS!I10/BS!I22 -> 2.5448565 | ... K12: =BS!K10/BS!K22 -> 1.8088348
A13: Quick Ratio | B13: =(BS!B6+BS!B7)/BS!B22 -> 3.1024021 | C13: =(BS!C6+BS!C7)/BS!C22 -> 2.6415532 | D13: =(BS!D6+BS!D7)/BS!D22 -> 3.3312184 | E13: =(BS!E6+BS!E7)/BS!E22 -> 3.2053807 | F13: =(BS!F6+BS!F7)/BS!F22 -> 2.7909961 | G13: =(BS!G6+BS!G7)/BS!G22 -> 2.2009872 | H13: =(BS!H6+BS!H7)/BS!H22 -> 2.0037879 | I13: =(BS!I6+BS!I7)/BS!I22 -> 1.9421747 | ... K13: =(BS!K6+BS!K7)/BS!K22 -> 1.1357628
A14: Cash Ratio | B14: =BS!B6/BS!B22 -> 2.4082786 | C14: =BS!C6/BS!C22 -> 2.0150293 | D14: =BS!D6/BS!D22 -> 2.4754136 | E14: =BS!E6/BS!E22 -> 2.3260544 | F14: =BS!F6/BS!F22 -> 1.8592698 | G14: =BS!G6/BS!G22 -> 1.405462 | H14: =BS!H6/BS!H22 -> 1.1173763 | I14: =BS!I6/BS!I22 -> 1.1337105 | ... K14: =BS!K6/BS!K22 -> 0.48695963
A15: Defensive Interval | B15: =BS!B10/(SUM(IS!B8:B12)/365) -> 427.93103 | C15: =BS!C10/(SUM(IS!C8:C12)/365) -> 448.62447 | D15: =BS!D10/(SUM(IS!D8:D12)/365) -> 416.42443 | E15: =BS!E10/(SUM(IS!E8:E12)/365) -> 392.98968 | F15: =BS!F10/(SUM(IS!F8:F12)/365) -> 353.11809 | G15: =BS!G10/(SUM(IS!G8:G12)/365) -> 308.78282 | H15: =BS!H10/(SUM(IS!H8:H12)/365) -> 290.70457 | I15: =BS!I10/(SUM(IS!I8:I12)/365) -> 305.4096 | ... K15: =BS!K10/(SUM(IS!K8:K12)/365) -> 231.74723
A17: Solvency Ratios | B17: FY 2014 | C17: FY 2015 | D17: FY 2016 | E17: FY 2017 | F17: FY 2018 | G17: FY 2019 | H17: FY 2020 | I17: FY 2021 | J17: FY 2022 | K17: FY 2023
A18: A/E | B18: =BS!B18/BS!B33 -> 1.2792724 | C18: =BS!C18/BS!C33 -> 1.3065476 | D18: =BS!D18/BS!D33 -> 1.2162801 | E18: =BS!E18/BS!E33 -> 1.2053579 | F18: =BS!F18/BS!F33 -> 1.2221829 | G18: =BS!G18/BS!G33 -> 1.2932037 | H18: =BS!H18/BS!H33 -> 1.3942045 | I18: =BS!I18/BS!I33 -> 1.400211 | ... K18: =BS!K18/BS!K33 -> 1.6438551
A19: D/E | B19: =BS!B23/BS!B33 -> 0 | C19: =BS!C23/BS!C33 -> 0 | D19: =BS!D23/BS!D33 -> 0 | E19: =BS!E23/BS!E33 -> 0 | F19: =BS!F23/BS!F33 -> 0 | G19: =BS!G23/BS!G33 -> 0 | H19: =BS!H23/BS!H33 -> 0.060962274 | I19: =BS!I23/BS!I33 -> 0.059740564 | ... K19: =BS!K23/BS!K33 -> 0.093106405
A20: D/A | B20: =BS!B23/BS!B18 -> 0 | C20: =BS!C23/BS!C18 -> 0 | D20: =BS!D23/BS!D18 -> 0 | E20: =BS!E23/BS!E18 -> 0 | F20: =BS!F23/BS!F18 -> 0 | G20: =BS!G23/BS!G18 -> 0 | H20: =BS!H23/BS!H18 -> 0.04372549 | I20: =BS!I23/BS!I18 -> 0.042665402 | ... K20: =BS!K23/BS!K18 -> 0.056639057
A21: Interest Coverage Ratio | B21: =IFERROR(IS!B15/IS!B16,"NA") -> 1637.4444 | C21: =IFERROR(IS!C15/IS!C16,"NA") -> 1441.3333 | D21: =IFERROR(IS!D15/IS!D16,"NA") -> NA | E21: =IFERROR(IS!E15/IS!E16,"NA") -> NA | F21: =IFERROR(IS!F15/IS!F16,"NA") -> NA | G21: =IFERROR(IS!G15/IS!G16,"NA") -> NA | H21: =IFERROR(IS!H15/IS!H16,"NA") -> 130.45294 | I21: =IFERROR(IS!I15/IS!I16,"NA") -> 137.55385 | ... K21: =IFERROR(IS!K15/IS!K16,"NA") -> 118.33099
A23: Activity Ratios | B23: FY 2014 | C23: FY 2015 | D23: FY 2016 | E23: FY 2017 | F23: FY 2018 | G23: FY 2019 | H23: FY 2020 | I23: FY 2021 | J23: FY 2022 | K23: FY 2023
A24: Asset Turnover Ratio | C24: =IS!C6/AVERAGE(BS!B18:C18) -> 0.92083891 | D24: =IS!D6/AVERAGE(BS!C18:D18) -> 0.92739785 | E24: =IS!E6/AVERAGE(BS!D18:E18) -> 0.90408604 | F24: =IS!F6/AVERAGE(BS!E18:F18) -> 0.90873062 | G24: =IS!G6/AVERAGE(BS!F18:G18) -> 1.0471132 | H24: =IS!H6/AVERAGE(BS!G18:H18) -> 1.0643786 | I24: =IS!I6/AVERAGE(BS!H18:I18) -> 1.0302793 | J24: =IS!J6/AVERAGE(BS!I18:J18) -> 1.1053871 | K24: =IS!K6/AVERAGE(BS!J18:K18) -> 1.2387279
A25: Receivables Turnover Ratio | C25: =IS!C6/AVERAGE(BS!B7:C7) -> 6.2831045 | D25: =IS!D6/AVERAGE(BS!C7:D7) -> 6.2311457 | E25: =IS!E6/AVERAGE(BS!D7:E7) -> 6.0488754 | F25: =IS!F6/AVERAGE(BS!E7:F7) -> 5.7990104 | G25: =IS!G6/AVERAGE(BS!F7:G7) -> 6.1179878 | H25: =IS!H6/AVERAGE(BS!G7:H7) -> 5.618899 | I25: =IS!I6/AVERAGE(BS!H7:I7) -> 5.4351658 | J25: =IS!J6/AVERAGE(BS!I7:J7) -> 5.9028386 | K25: =IS!K6/AVERAGE(BS!J7:K7) -> 6.2120444
A26: Inventory Turnover Ratio | C26: =IFERROR(IS!C8+IS!C12/AVERAGE(BS!B8:C8),"NA") -> NA | D26: =IFERROR(IS!D8+IS!D12/AVERAGE(BS!C8:D8),"NA") -> NA | E26: =IFERROR(IS!E8+IS!E12/AVERAGE(BS!D8:E8),"NA") -> NA | F26: =IFERROR(IS!F8+IS!F12/AVERAGE(BS!E8:F8),"NA") -> NA | G26: =IFERROR(IS!G8+IS!G12/AVERAGE(BS!F8:G8),"NA") -> NA | H26: =IFERROR(IS!H8+IS!H12/AVERAGE(BS!G8:H8),"NA") -> NA | I26: =IFERROR(IS!I8+IS!I12/AVERAGE(BS!H8:I8),"NA") -> NA | J26: =IFERROR(IS!J8+IS!J12/AVERAGE(BS!I8:J8),"NA") -> NA | K26: =IFERROR(IS!K8+IS!K12/AVERAGE(BS!J8:K8),"NA") -> NA
A27: Payables Turnover Ratio | C27: =IS!C8+IS!C12/AVERAGE(BS!B19:C19) -> 32.083067 | D27: =IS!D8+IS!D12/AVERAGE(BS!C19:D19) -> 20.721582 | E27: =IS!E8+IS!E12/AVERAGE(BS!D19:E19) -> 16.777778 | F27: =IS!F8+IS!F12/AVERAGE(BS!E19:F19) -> 12.667722 | G27: =IS!G8+IS!G12/AVERAGE(BS!F19:G19) -> 7.1748428 | H27: =IS!H8+IS!H12/AVERAGE(BS!G19:H19) -> 4.402343 | I27: =IS!I8+IS!I12/AVERAGE(BS!H19:I19) -> 4.4564086 | J27: =IS!J8+IS!J12/AVERAGE(BS!I19:J19) -> 5.7290595 | K27: =IS!K8+IS!K12/AVERAGE(BS!J19:K19) -> 6.1043497
A28: Receivable Days (DSO) | C28: =365/C25 -> 58.092301 | D28: =365/D25 -> 58.576707 | E28: =365/E25 -> 60.341796 | F28: =365/F25 -> 62.941774 | G28: =365/G25 -> 59.660139 | H28: =365/H25 -> 64.959346 | I28: =365/I25 -> 67.155265 | J28: =365/J25 -> 61.834657 | K28: =365/K25 -> 58.756824
A29: Inventory Days (DIH) | C29: 0 | D29: 0 | E29: 0 | F29: 0 | G29: 0 | H29: 0 | I29: 0 | J29: 0 | K29: 0
A30: Payable Days | C30: =365/C27 -> 11.376718 | D30: =365/D27 -> 17.614486 | E30: =365/E27 -> 21.754967 | F30: =365/F27 -> 28.81339 | G30: =365/G27 -> 50.872195 | H30: =365/H27 -> 82.910395 | I30: =365/I27 -> 81.904519 | J30: =365/J27 -> 63.710283 | K30: =365/K27 -> 59.793429
A32: Operating Cycle | C32: =C28+C29 -> 58.092301 | D32: =D28+D29 -> 58.576707 | E32: =E28+E29 -> 60.341796 | F32: =F28+F29 -> 62.941774 | G32: =G28+G29 -> 59.660139 | H32: =H28+H29 -> 64.959346 | I32: =I28+I29 -> 67.155265 | J32: =J28+J29 -> 61.834657 | K32: =K28+K29 -> 58.756824
A33: Net Operating Cycle (CCC) | C33: =C28+C29-C30 -> 46.715583 | D33: =D28+D29-D30 -> 40.962222 | E33: =E28+E29-E30 -> 38.586829 | F33: =F28+F29-F30 -> 34.128384 | G33: =G28+G29-G30 -> 8.7879439 | H33: =H28+H29-H30 -> -17.951049 | I33: =I28+I29-I30 -> -14.749254 | J33: =J28+J29-J30 -> -1.8756261 | K33: =K28+K29-K30 -> -1.0366044
