Workbook

Sheet IS
A2: Tata Consultancy Services Ltd (TCS) | L2: 2014 | M2: 2015 | N2: 2016 | O2: 2017 | P2: 2018 | Q2: 2019 | R2: 2020 | S2: 2021 | T2: 2022 | U2: 2023
A5: Income Statement (All numbers in INR crores except EPS and DPS) | B5: FY 2014 | C5: FY 2015 | D5: FY 2016 | E5: FY 2017 | F5: FY 2018 | G5: FY 2019 | H5: FY 2020 | I5: FY 2021 | J5: FY 2022 | K5: FY 2023
A6: 'Total Revenue' | B6: 83446.1 | C6: 98368.07 | D6: 111730 | E6: 122187 | F6: 126746 | G6: 150774 | H6: 161541 | I6: 167311 | J6: 195772 | K6: 228907
A7: y-o-y growth in revenue | C7: =C6/B6-1 -> 0.17882166 | D7: =D6/C6-1 -> 0.13583605 | E7: =E6/D6-1 -> 0.093591694 | F7: =F6/E6-1 -> 0.037311662 | G7: =G6/F6-1 -> 0.189576 | H7: =H6/G6-1 -> 0.071411517 | I7: =I6/H6-1 -> 0.035718486 | J7: =J6/I6-1 -> 0.17010836 | K7: =K6/J6-1 -> 0.16925301
A8: '- Raw Materials' | B8: 0 | C8: 0 | D8: 0 | E8: 94 | F8: 86 | G8: 40 | H8: 18 | I8: 14 | J8: 29 | K8: 37
A9: '- Power & Fuel Cost' | B9: 527.1 | C9: 573.87 | D9: 0 | E9: 0 | F9: 0 | G9: 0 | H9: 0 | I9: 0 | J9: 0 | K9: 0
A10: '- Employee Cost' | B10: 29860.01 | C10: 38701.15 | D10: 55348 | E10: 61621 | F10: 66396 | G10: 78246 | H10: 85952 | I10: 91814 | J10: 107554 | K10: 127522
A11: '- Selling & Administrative Expenses' | B11: 4278.52 | C11: 4842.25 | D11: 15589 | E11: 16392 | F11: 16808 | G11: 20387 | H11: 20527 | I11: 18322 | J11: 23187 | K11: 28913
A12: '- Operating & Other expenses' | B12: 21990.94 | C12: 26049.43 | D12: 7032 | E12: 7548 | F12: 7298 | G12: 8284 | H12: 8343 | I12: 8699 | J12: 7927 | K12: 9727
A13: '= EBITDA' | B13: 26789.53 | C13: 28201.37 | D13: 33761 | E13: 36532 | F13: 36158 | G13: 43817 | H13: 46701 | I13: 48462 | J13: 57075 | K13: 62708
A14: '- Depreciation/Amortization' | B14: 1349.15 | C14: 1798.69 | D14: 1888 | E14: 1987 | F14: 2014 | G14: 2056 | H14: 3529 | I14: 4065 | J14: 4604 | K14: 5022
A15: '= PBIT' | B15: 25440.38 | C15: 26402.68 | D15: 31873 | E15: 34545 | F15: 34144 | G15: 41761 | H15: 43172 | I15: 44397 | J15: 52471 | K15: 57686
A16: '- Interest & Other Items' | B16: 38.52 | C16: 104.19 | D16: 33 | E16: 32 | F16: 52 | G16: 198 | H16: 924 | I16: 637 | J16: 784 | K16: 779
A17: '= PBT' | B17: 25401.86 | C17: 26298.49 | D17: 31840 | E17: 34513 | F17: 34092 | G17: 41563 | H17: 42248 | I17: 43760 | J17: 51687 | K17: 56907
A18: '- Taxes & Other Items' | B18: 6237.99 | C18: 6446.31 | D18: 7570 | E18: 8224 | F18: 8266 | G18: 10091 | H18: 9908 | I18: 11330 | J18: 13360 | K18: 14760
A19: '= Net Income' | B19: 19163.87 | C19: 19852.18 | D19: 24270 | E19: 26289 | F19: 25826 | G19: 31472 | H19: 32340 | I19: 32430 | J19: 38327 | K19: 42147
... A23: 'Payout ratio' | B23: 0.33 | C23: 0.78 | D23: 0.35 | E23: 0.35 | F23: 0.38 | G23: 0.36 | H23: 0.85 | I23: 0.44 | J23: 0.41 | K23: 1
A26: EBITDA MARGIN | B26: =B13/B6 -> 0.32103993 | C26: =C13/C6 -> 0.28669232 | D26: =D13/D6 -> 0.30216594 | E26: =E13/E6 -> 0.29898434 | F26: =F13/F6 -> 0.28527922 | G26: =G13/G6 -> 0.29061377 | H26: =H13/H6 -> 0.28909689 | I26: =I13/I6 -> 0.2896522 | ... K26: =K13/K6 -> 0.27394531
A27: EBIT MARGIN | B27: =B15/B6 -> 0.30487201 | C27: =C15/C6 -> 0.26840701 | D27: =D15/D6 -> 0.28526806 | E27: =E15/E6 -> 0.28272238 | F27: =F15/F6 -> 0.26938917 | G27: =G15/G6 -> 0.27697746 | H27: =H15/H6 -> 0.26725104 | I27: =I15/I6 -> 0.26535613 | ... K27: =K15/K6 -> 0.25200627
A28: EBT MARGIN | B28: =B17/B6 -> 0.30441039 | C28: =C17/C6 -> 0.26734783 | D28: =D17/D6 -> 0.2849727 | E28: =E17/E6 -> 0.28246049 | F28: =F17/F6 -> 0.2689789 | G28: =G17/G6 -> 0.27566424 | H28: =H17/H6 -> 0.26153113 | I28: =I17/I6 -> 0.26154885 | ... K28: =K17/K6 -> 0.24860314
A29: PAT MARGIN | B29: =B19/B6 -> 0.22965567 | C29: =C19/C6 -> 0.20181528 | D29: =D19/D6 -> 0.21722008 | E29: =E19/E6 -> 0.21515382 | F29: =F19/F6 -> 0.20376185 | G29: =G19/G6 -> 0.20873625 | H29: =H19/H6 -> 0.20019685 | I29: =I19/I6 -> 0.19383065 | ... K29: =K19/K6 -> 0.18412281

Sheet BS
A2: Tata Consultancy Services Ltd (TCS)
A5: Balance Sheet (All numbers in INR crores) | B5: FY 2014 | C5: FY 2015 | D5: FY 2016 | E5: FY 2017 | F5: FY 2018 | G5: FY 2019 | H5: FY 2020 | I5: FY 2021 | J5: FY 2022 | K5: FY 2023
A6: 'Cash and Short Term Investments' | B6: 15600.31 | C6: 20048.64 | D6: 29267 | E6: 45785 | F6: 42868 | G6: 41939 | H6: 35806 | I6: 38489 | J6: 48483 | K6: 47929
A7: '+ Total Receivables' | B7: 18230.4 | C7: 20437.94 | D7: 24073 | E7: 22617 | F7: 24943 | G7: 27346 | H7: 30532 | I7: 30079 | J7: 41810 | K7: 49954
A8: '+ Total Inventory' | B8: 15.21 | C8: 16.07 | D8: 16 | E8: 21 | F8: 26 | G8: 10 | H8: 5 | I8: 8 | J8: 20 | K8: 28
A9: '+ Other Current Assets' | B9: 9051.77 | C9: 8310.35 | D9: 9857 | E9: 11893 | F9: 13387 | G9: 22836 | H9: 23894 | I9: 30704 | J9: 17997 | K9: 12359
A10: '= Total Current Assets (A1)' | B10: 42897.69 | C10: 48813 | D10: 63213 | E10: 80316 | F10: 81224 | G10: 92131 | H10: 90237 | I10: 99280 | J10: 108310 | K10: 110270
A11: 'Loans & Advances' | B11: - | C11: - | D11: - | E11: - | F11: - | G11: - | H11: - | I11: - | J11: - | K11: -
A12: '+ Net Property/Plant/Equipment' | B12: 10250.58 | C12: 12142.49 | D12: 11649 | E12: 11598 | F12: 11494 | G12: 11399 | H12: 19856 | I12: 19674 | J12: 19615 | K12: 19024
A13: '+ Goodwill & Intangibles' | B13: 2462.23 | C13: 2262.05 | D13: 1795 | E13: 1644 | F13: 1757 | G13: 1854 | H13: 1978 | I13: 2273 | J13: 2888 | K13: 2725
A14: '+ Long Term Investments' | B14: 2275.27 | C14: 169.18 | D14: 343 | E14: 344 | F14: 301 | G14: 239 | H14: 216 | I14: 213 | J14: 223 | K14: 266
A15: '+ Deferred Tax Assets (Net)' | B15: 111.26 | C15: 250.98 | D15: 2103 | E15: 1909 | F15: 2279 | G15: 1614 | H15: 2049 | I15: 3164 | J15: 3118 | K15: 2515
A16: '+ Other Assets' | B16: 8831.95 | C16: 9680.22 | D16: 9188 | E16: 6522 | F16: 8071 | G16: 6664 | H16: 5784 | I16: 5388 | J16: 6770 | K16: 8059
A17: '= Non Current Assets (A2)' | B17: 23931.29 | C17: 24504.92 | D17: 25078 | E17: 22017 | F17: 23902 | G17: 21770 | H17: 29883 | I17: 30712 | J17: 32614 | K17: 32589
A18: 'Total Assets (A1 + A2)' | B18: 66828.98 | C18: 73317.92 | D18: 88291 | E18: 102333 | F18: 105126 | G18: 113901 | H18: 120120 | I18: 129992 | J18: 140924 | K18: 142859
A19: 'Accounts Payable' | B19: 6023.55 | C19: 9168.34 | D19: 7872 | E19: 5192 | F19: 5356 | G19: 6595 | H19: 7242 | I19: 8259 | J19: 8816 | K19: 11246
A20: '+ Total Deposits' | B20: - | C20: - | D20: - | E20: - | F20: - | G20: - | H20: - | I20: - | J20: - | K20: -
A21: '+ Other Current Liabilities' | B21: 9646.76 | C21: 11149.9 | D21: 7697 | E21: 9320 | F21: 12472 | G21: 15489 | H21: 19818 | I21: 25896 | J21: 33535 | K21: 32312
A22: '= Current Liabilities' | B22: 15670.31 | C22: 20318.24 | D22: 15569 | E22: 14512 | F22: 17828 | G22: 22084 | H22: 27060 | I22: 34155 | J22: 42351 | K22: 43558
A23: 'Total Long Term Debt' | B23: 127.26 | C23: 114.27 | D23: 83 | E23: 71 | F23: 54 | G23: 44 | H23: 6906 | I23: 6503 | J23: 6368 | K23: 6203
A24: '+ Deferred Tax Liabilities (Net)' | B24: - | C24: - | D24: - | E24: - | F24: - | G24: - | H24: - | I24: - | J24: - | K24: -
A25: '+ Other Liabilities' | B25: 1128.66 | C25: 1122.89 | D25: 1212 | E25: 1170 | F25: 1714 | G25: 1874 | H25: 1405 | I25: 2226 | J25: 2359 | K25: 1892
A26: '= Non Current Liabilities' | B26: 1255.92 | C26: 1237.16 | D26: 1295 | E26: 1241 | F26: 1768 | G26: 1918 | H26: 8311 | I26: 8729 | J26: 8727 | K26: 8095
A27: 'Total Liabilities' | B27: 16926.23 | C27: 21555.4 | D27: 16864 | E27: 15753 | F27: 19596 | G27: 24002 | H27: 35371 | I27: 42884 | J27: 51078 | K27: 51653
A28: 'Common Stock' | B28: 195.87 | C28: 195.87 | D28: 197 | E28: 197 | F28: 191 | G28: 375 | H28: 375 | I28: 370 | J28: 366 | K28: 366
A29: '+ Additional Paid-in Capital' | B29: 1918.87 | C29: 1918.87 | D29: 1919 | E29: 1919 | F29: 0 | G29: 0 | H29: 0 | I29: 0 | J29: 0 | K29: 0
A30: '+ Reserves & Surplus' | B30: 47080.02 | C30: 48520.02 | D30: 68956 | E30: 84098 | F30: 84937 | G30: 89071 | H30: 83751 | I30: 86063 | J30: 88773 | K30: 90058
A31: '+ Minority Interest' | B31: 707.99 | C31: 1127.76 | D31: 355 | E31: 366 | F31: 402 | G31: 453 | H31: 623 | I31: 675 | J31: 707 | K31: 782
A32: '+ Other Equity' | B32: 0 | C32: 0 | D32: 0 | E32: 0 | F32: 0 | G32: 0 | H32: 0 | I32: 0 | J32: 0 | K32: 0
A33: 'Total Equity' | B33: 49902.75 | C33: 51762.52 | D33: 71427 | E33: 86580 | F33: 85530 | G33: 89899 | H33: 84749 | I33: 87108 | J33: 89846 | K33: 91206
A34: 'Total Liabilities & Shareholder's Equity' | B34: 66828.98 | C34: 73317.92 | D34: 88291 | E34: 102333 | F34: 105126 | G34: 113901 | H34: 120120 | I34: 129992 | J34: 140924 | K34: 142859
A39: Current Ratio | B39: =B10/B22 -> 2.7375138 | C39: =C10/C22 -> 2.4024227 | D39: =D10/D22 -> 4.0601837 | E39: =E10/E22 -> 5.5344542 | F39: =F10/F22 -> 4.5559794 | G39: =G10/G22 -> 4.1718439 | H39: =H10/H22 -> 3.3347007 | I39: =I10/I22 -> 2.9067486 | ... K39: =K10/K22 -> 2.5315671
A40: Quick Ratio | B40: =(B6+B7)/B22 -> 2.158905 | C40: =(C6+C7)/C22 -> 1.9926224 | D40: =(D6+D7)/D22 -> 3.4260389 | E40: =(E6+E7)/E22 -> 4.7134785 | F40: =(F6+F7)/F22 -> 3.8036235 | G40: =(G6+G7)/G22 -> 3.1373393 | H40: =(H6+H7)/H22 -> 2.4515152 | I40: =(I6+I7)/I22 -> 2.0075538 | ... K40: =(K6+K7)/K22 -> 2.2471877
A41: Cash Ratio | B41: =B6/B22 -> 0.99553295 | C41: =C6/C22 -> 0.98673113 | D41: =D6/D22 -> 1.8798253 | E41: =E6/E22 -> 3.1549752 | F41: =F6/F22 -> 2.4045322 | G41: =G6/G22 -> 1.8990672 | H41: =H6/H22 -> 1.3232077 | I41: =I6/I22 -> 1.1268921 | ... K41: =K6/K22 -> 1.100349
A43: A/E | B43: =B18/B33 -> 1.3391843 | C43: =C18/C33 -> 1.4164287 | D43: =D18/D33 -> 1.2361012 | E43: =E18/E33 -> 1.1819473 | F43: =F18/F33 -> 1.2291126 | G43: =G18/G33 -> 1.2669885 | H43: =H18/H33 -> 1.4173619 | I43: =I18/I33 -> 1.4923084 | ... K43: =K18/K33 -> 1.5663334
A44: D/E | B44: =B27/B33 -> 0.33918431 | C44: =C27/C33 -> 0.41642872 | D44: =D27/D33 -> 0.23610119 | E44: =E27/E33 -> 0.18194733 | F44: =F27/F33 -> 0.22911259 | G44: =G27/G33 -> 0.26698851 | H44: =H27/H33 -> 0.41736186 | I44: =I27/I33 -> 0.4923084 | ... K44: =K27/K33 -> 0.56633336
A45: D/A | B45: =B27/B18 -> 0.2532768 | C45: =C27/C18 -> 0.29399907 | D45: =D27/D18 -> 0.19100475 | E45: =E27/E18 -> 0.15393861 | F45: =F27/F18 -> 0.18640489 | G45: =G27/G18 -> 0.21072686 | H45: =H27/H18 -> 0.29446387 | I45: =I27/I18 -> 0.32989722 | ... K45: =K27/K18 -> 0.3615663

Sheet CFS
A2: Tata Consultancy Services Ltd (TCS)
A5: Cash Flow Statement (All numbers in INR crores) | B5: FY 2014 | C5: FY 2015 | D5: FY 2016 | E5: FY 2017 | F5: FY 2018 | G5: FY 2019 | H5: FY 2020 | I5: FY 2021 | J5: FY 2022 | K5: FY 2023
A6: 'Cash from Operating Activities' | B6: 14751.41 | C6: 19368.78 | D6: 19109 | E6: 25223 | F6: 25067 | G6: 28593 | H6: 32369 | I6: 38802 | J6: 39949 | K6: 41965
A7: '+ Cash from Investing Activities' | B7: -9451.67 | C7: -1807.14 | D7: -5010 | E7: -16895 | F7: 3104 | G7: 1645 | H7: 8968 | I7: -7956 | J7: -738 | K7: 548
A8: '+ Cash from Financing Activities' | B8: -5673.24 | C8: -17167.61 | D8: -9666 | E8: -11026 | F8: -26885 | G8: -27897 | H8: -39915 | I8: -32634 | J8: -33581 | K8: -47878
A9: '= Net Change in Cash' | B9: -373.5 | C9: 394.03 | D9: 4433 | E9: -2698 | F9: 1286 | G9: 2341 | H9: 1422 | I9: -1788 | J9: 5630 | K9: -5365
A10: 'Changes in Working Capital' | B10: -10494.42 | C10: -6734.54 | D10: -12522 | E10: -8577 | F10: -7818 | G10: -12127 | H10: -10513 | I10: -8229 | J10: -14255 | K10: -17183
A11: 'Capital Expenditures' | B11: 3126.15 | C11: 2949.2 | D11: 1987 | E11: 1989 | F11: 1862 | G11: 2231 | H11: 2730 | I11: 3176 | J11: 2995 | K11: 3100
A12: 'Free Cash Flow' | B12: 11625.26 | C12: 16419.58 | D12: 17122 | E12: 23234 | F12: 23205 | G12: 26362 | H12: 29639 | I12: 35626 | J12: 36954 | K12: 38865

Sheet Ratio Analysis-tcs
A2: Profitability Ratios | B2: FY 2014 | C2: FY 2015 | D2: FY 2016 | E2: FY 2017 | F2: FY 2018 | G2: FY 2019 | H2: FY 2020 | I2: FY 2021 | J2: FY 2022 | K2: FY 2023
A3: EBITDA Margin | B3: =IS!B26 -> 0.32103993 | C3: =IS!C26 -> 0.28669232 | D3: =IS!D26 -> 0.30216594 | E3: =IS!E26 -> 0.29898434 | F3: =IS!F26 -> 0.28527922 | G3: =IS!G26 -> 0.29061377 | H3: =IS!H26 -> 0.28909689 | I3: =IS!I26 -> 0.2896522 | ... K3: =IS!K26 -> 0.27394531
A4: EBIT Margin | B4: =IS!B27 -> 0.30487201 | C4: =IS!C27 -> 0.26840701 | D4: =IS!D27 -> 0.28526806 | E4: =IS!E27 -> 0.28272238 | F4: =IS!F27 -> 0.26938917 | G4: =IS!G27 -> 0.27697746 | H4: =IS!H27 -> 0.26725104 | I4: =IS!I27 -> 0.26535613 | ... K4: =IS!K27 -> 0.25200627
A5: EBT Margin | B5: =IS!B28 -> 0.30441039 | C5: =IS!C28 -> 0.26734783 | D5: =IS!D28 -> 0.2849727 | E5: =IS!E28 -> 0.28246049 | F5: =IS!F28 -> 0.2689789 | G5: =IS!G28 -> 0.27566424 | H5: =IS!H28 -> 0.26153113 | I5: =IS!I28 -> 0.26154885 | ... K5: =IS!K28 -> 0.24860314
A6: PAT Margin | B6: =IS!B29 -> 0.22965567 | C6: =IS!C29 -> 0.20181528 | D6: =IS!D29 -> 0.21722008 | E6: =IS!E29 -> 0.21515382 | F6: =IS!F29 -> 0.20376185 | G6: =IS!G29 -> 0.20873625 | H6: =IS!H29 -> 0.20019685 | I6: =IS!I29 -> 0.19383065 | ... K6: =IS!K29 -> 0.18412281
A7: ROA | C7: =IS!C19/AVERAGE(BS!B18:C18) -> 0.2833053 | D7: =IS!D19/AVERAGE(BS!C18:D18) -> 0.30035471 | E7: =IS!E19/AVERAGE(BS!D18:E18) -> 0.27582046 | F7: =IS!F19/AVERAGE(BS!E18:F18) -> 0.2489745 | G7: =IS!G19/AVERAGE(BS!F18:G18) -> 0.28738009 | H7: =IS!H19/AVERAGE(BS!G18:H18) -> 0.27638545 | I7: =IS!I19/AVERAGE(BS!H18:I18) -> 0.25932382 | J7: =IS!J19/AVERAGE(BS!I18:J18) -> 0.28294379 | K7: =IS!K19/AVERAGE(BS!J18:K18) -> 0.29703682
A8: ROE | C8: =IS!C19/AVERAGE(BS!B33:C33) -> 0.39054005 | D8: =IS!D19/AVERAGE(BS!C33:D33) -> 0.39402702 | E8: =IS!E19/AVERAGE(BS!D33:E33) -> 0.33275741 | F8: =IS!F19/AVERAGE(BS!E33:F33) -> 0.30011039 | G8: =IS!G19/AVERAGE(BS!F33:G33) -> 0.35880043 | H8: =IS!H19/AVERAGE(BS!G33:H33) -> 0.37034492 | I8: =IS!I19/AVERAGE(BS!H33:I33) -> 0.3774068 | J8: =IS!J19/AVERAGE(BS!I33:J33) -> 0.43318603 | K8: =IS!K19/AVERAGE(BS!J33:K33) -> 0.46557895
A9: ROCE | C9: {=IS!C15/AVERAGE(BS!B33:C33+AVERAGE(BS!B23:C23))} -> 0.51817308 | D9: {=IS!D15/AVERAGE(BS!C33:D33+AVERAGE(BS!C23:D23))} -> 0.51663553 | E9: {=IS!E15/AVERAGE(BS!D33:E33+AVERAGE(BS!D23:E23))} -> 0.43683335 | F9: {=IS!F15/AVERAGE(BS!E33:F33+AVERAGE(BS!E23:F23))} -> 0.39648155 | G9: {=IS!G15/AVERAGE(BS!F33:G33+AVERAGE(BS!F23:G23))} -> 0.47583563 | H9: {=IS!H15/AVERAGE(BS!G33:H33+AVERAGE(BS!G23:H23))} -> 0.47546779 | I9: {=IS!I15/AVERAGE(BS!H33:I33+AVERAGE(BS!H23:I23))} -> 0.47927844 | J9: {=IS!J15/AVERAGE(BS!I33:J33+AVERAGE(BS!I23:J23))} -> 0.55283551 | K9: {=IS!K15/AVERAGE(BS!J33:K33+AVERAGE(BS!J23:K23))} -> 0.59585896
A11: Liquidity Ratios | B11: FY 2014 | C11: FY 2015 | D11: FY 2016 | E11: FY 2017 | F11: FY 2018 | G11: FY 2019 | H11: FY 2020 | I11: FY 2021 | J11: FY 2022 | K11: FY 2023
A12: Current Ratio | B12: =BS!B39 -> 2.7375138 | C12: =BS!C39 -> 2.4024227 | D12: =BS!D39 -> 4.0601837 | E12: =BS!E39 -> 5.5344542 | F12: =BS!F39 -> 4.5559794 | G12: =BS!G39 -> 4.1718439 | H12: =BS!H39 -> 3.3347007 | I12: =BS!I39 -> 2.9067486 | ... K12: =BS!K39 -> 2.5315671
A13: Quick Ratio | B13: =BS!B40 -> 2.158905 | C13: =BS!C40 -> 1.9926224 | D13: =BS!D40 -> 3.4260389 | E13: =BS!E40 -> 4.7134785 | F13: =BS!F40 -> 3.8036235 | G13: =BS!G40 -> 3.1373393 | H13: =BS!H40 -> 2.4515152 | I13: =BS!I40 -> 2.0075538 | ... K13: =BS!K40 -> 2.2471877
A14: Cash Ratio | B14: =BS!B41 -> 0.99553295 | C14: =BS!C41 -> 0.98673113 | D14: =BS!D41 -> 1.8798253 | E14: =BS!E41 -> 3.1549752 | F14: =BS!F41 -> 2.4045322 | G14: =BS!G41 -> 1.8990672 | H14: =BS!H41 -> 1.3232077 | I14: =BS!I41 -> 1.1268921 | ... K14: =BS!K41 -> 1.100349
A15: Defensive Interval | B15: =BS!B10/(SUM(IS!B8:B12)/365) -> 276.36083 | C15: =BS!C10/(SUM(IS!C8:C12)/365) -> 253.92024 | D15: =BS!D10/(SUM(IS!D8:D12)/365) -> 295.92203 | E15: =BS!E10/(SUM(IS!E8:E12)/365) -> 342.24902 | F15: =BS!F10/(SUM(IS!F8:F12)/365) -> 327.27028 | G15: =BS!G10/(SUM(IS!G8:G12)/365) -> 314.40499 | H15: =BS!H10/(SUM(IS!H8:H12)/365) -> 286.80342 | I15: =BS!I10/(SUM(IS!I8:I12)/365) -> 304.90118 | ... K15: =BS!K10/(SUM(IS!K8:K12)/365) -> 242.17083
A17: Solvency Ratios | B17: FY 2014 | C17: FY 2015 | D17: FY 2016 | E17: FY 2017 | F17: FY 2018 | G17: FY 2019 | H17: FY 2020 | I17: FY 2021 | J17: FY 2022 | K17: FY 2023
A18: A/E | B18: =BS!B43 -> 1.3391843 | C18: =BS!C43 -> 1.4164287 | D18: =BS!D43 -> 1.2361012 | E18: =BS!E43 -> 1.1819473 | F18: =BS!F43 -> 1.2291126 | G18: =BS!G43 -> 1.2669885 | H18: =BS!H43 -> 1.4173619 | I18: =BS!I43 -> 1.4923084 | ... K18: =BS!K43 -> 1.5663334
A19: D/E | B19: =BS!B44 -> 0.33918431 | C19: =BS!C44 -> 0.41642872 | D19: =BS!D44 -> 0.23610119 | E19: =BS!E44 -> 0.18194733 | F19: =BS!F44 -> 0.22911259 | G19: =BS!G44 -> 0.26698851 | H19: =BS!H44 -> 0.41736186 | I19: =BS!I44 -> 0.4923084 | ... K19: =BS!K44 -> 0.56633336
A20: D/A | B20: =BS!B45 -> 0.2532768 | C20: =BS!C45 -> 0.29399907 | D20: =BS!D45 -> 0.19100475 | E20: =BS!E45 -> 0.15393861 | F20: =BS!F45 -> 0.18640489 | G20: =BS!G45 -> 0.21072686 | H20: =BS!H45 -> 0.29446387 | I20: =BS!I45 -> 0.32989722 | ... K20: =BS!K45 -> 0.3615663
A21: Interest Coverage Ratio | B21: =IS!B15/IS!B16 -> 660.446 | C21: =IS!C15/IS!C16 -> 253.40896 | D21: =IS!D15/IS!D16 -> 965.84848 | E21: =IS!E15/IS!E16 -> 1079.5312 | F21: =IS!F15/IS!F16 -> 656.61538 | G21: =IS!G15/IS!G16 -> 210.91414 | H21: =IS!H15/IS!H16 -> 46.722944 | I21: =IS!I15/IS!I16 -> 69.697017 | ... K21: =IS!K15/IS!K16 -> 74.051348
A23: Activity Ratios | B23: FY 2014 | C23: FY 2015 | D23: FY 2016 | E23: FY 2017 | F23: FY 2018 | G23: FY 2019 | H23: FY 2020 | I23: FY 2021 | J23: FY 2022 | K23: FY 2023
A24: Asset Turnover Ratio | C24: =IS!C6/AVERAGE(BS!B18:C18) -> 1.4037852 | D24: =IS!D6/AVERAGE(BS!C18:D18) -> 1.3827207 | E24: =IS!E6/AVERAGE(BS!D18:E18) -> 1.2819687 | F24: =IS!F6/AVERAGE(BS!E18:F18) -> 1.2218896 | G24: =IS!G6/AVERAGE(BS!F18:G18) -> 1.3767618 | H24: =IS!H6/AVERAGE(BS!G18:H18) -> 1.3805684 | I24: =IS!I6/AVERAGE(BS!H18:I18) -> 1.3378886 | J24: =IS!J6/AVERAGE(BS!I18:J18) -> 1.4452598 | K24: =IS!K6/AVERAGE(BS!J18:K18) -> 1.6132538
A25: Receivables Turnover Ratio | C25: =IS!C6/AVERAGE(BS!B7:C7) -> 5.0877834 | D25: =IS!D6/AVERAGE(BS!C7:D7) -> 5.0203388 | E25: =IS!E6/AVERAGE(BS!D7:E7) -> 5.2339687 | F25: =IS!F6/AVERAGE(BS!E7:F7) -> 5.3299411 | G25: =IS!G6/AVERAGE(BS!F7:G7) -> 5.7669491 | H25: =IS!H6/AVERAGE(BS!G7:H7) -> 5.582121 | I25: =IS!I6/AVERAGE(BS!H7:I7) -> 5.5208131 | J25: =IS!J6/AVERAGE(BS!I7:J7) -> 5.4465078 | K25: =IS!K6/AVERAGE(BS!J7:K7) -> 4.9890371
A26: Inventory Turnover Ratio | C26: =(IS!C8+IS!C12)/AVERAGE(BS!B8:C8) -> 1665.5646 | D26: =(IS!D8+IS!D12)/AVERAGE(BS!C8:D8) -> 438.54069 | E26: =(IS!E8+IS!E12)/AVERAGE(BS!D8:E8) -> 413.08108 | F26: =(IS!F8+IS!F12)/AVERAGE(BS!E8:F8) -> 314.21277 | G26: =(IS!G8+IS!G12)/AVERAGE(BS!F8:G8) -> 462.44444 | H26: =(IS!H8+IS!H12)/AVERAGE(BS!G8:H8) -> 1114.8 | I26: =(IS!I8+IS!I12)/AVERAGE(BS!H8:I8) -> 1340.4615 | J26: =(IS!J8+IS!J12)/AVERAGE(BS!I8:J8) -> 568.28571 | K26: =(IS!K8+IS!K12)/AVERAGE(BS!J8:K8) -> 406.83333
A27: Payables Turnover Ratio | C27: =(IS!C8+IS!C12)/AVERAGE(BS!B19:C19) -> 3.4293863 | D27: =(IS!D8+IS!D12)/AVERAGE(BS!C19:D19) -> 0.82533564 | E27: =(IS!E8+IS!E12)/AVERAGE(BS!D19:E19) -> 1.1699326 | F27: =(IS!F8+IS!F12)/AVERAGE(BS!E19:F19) -> 1.4000758 | G27: =(IS!G8+IS!G12)/AVERAGE(BS!F19:G19) -> 1.3930215 | H27: =(IS!H8+IS!H12)/AVERAGE(BS!G19:H19) -> 1.208499 | I27: =(IS!I8+IS!I12)/AVERAGE(BS!H19:I19) -> 1.1241855 | J27: =(IS!J8+IS!J12)/AVERAGE(BS!I19:J19) -> 0.93188873 | K27: =(IS!K8+IS!K12)/AVERAGE(BS!J19:K19) -> 0.97338251
A28: Receivable Days (DSO) | C28: =365/C25 -> 71.740475 | D28: =365/D25 -> 72.704256 | E28: =365/E25 -> 69.736756 | F28: =365/F25 -> 68.481057 | G28: =365/G25 -> 63.291698 | H28: =365/H25 -> 65.387332 | I28: =365/I25 -> 66.11345 | J28: =365/J25 -> 67.015418 | K28: =365/K25 -> 73.16041
A29: Inventory Days (DIH) | C29: =365/C26 -> 0.21914491 | D29: =365/D26 -> 0.83230589 | E29: =365/E26 -> 0.88360377 | F29: =365/F26 -> 1.1616333 | G29: =365/G26 -> 0.789284 | H29: =365/H26 -> 0.32741299 | I29: =365/I26 -> 0.27229427 | J29: =365/J26 -> 0.64228255 | K29: =365/K26 -> 0.89717329
A30: Payable Days | C30: =365/C27 -> 106.43304 | D30: =365/D27 -> 442.24432 | E30: =365/E27 -> 311.98377 | F30: =365/F27 -> 260.70016 | G30: =365/G27 -> 262.02036 | H30: =365/H27 -> 302.02757 | I30: =365/I27 -> 324.6795 | J30: =365/J27 -> 391.67766 | K30: =365/K27 -> 374.98105
A32: Operating Cycle | C32: =C28+C29 -> 71.95962 | D32: =D28+D29 -> 73.536562 | E32: =E28+E29 -> 70.62036 | F32: =F28+F29 -> 69.64269 | G32: =G28+G29 -> 64.080982 | H32: =H28+H29 -> 65.714745 | I32: =I28+I29 -> 66.385745 | J32: =J28+J29 -> 67.657701 | K32: =K28+K29 -> 74.057583
A33: Net Operating Cycle (CCC) | C33: =C28+C29-C30 -> -34.473416 | D33: =D28+D29-D30 -> -368.70776 | E33: =E28+E29-E30 -> -241.36341 | F33: =F28+F29-F30 -> -191.05747 | G33: =G28+G29-G30 -> -197.93938 | H33: =H28+H29-H30 -> -236.31282 | I33: =I28+I29-I30 -> -258.29376 | J33: =J28+J29-J30 -> -324.01996 | K33: =K28+K29-K30 -> -300.92347
